{
    "@class": "com.kony.gen.viz.model.container.KVizSegment2",
    "DNDConfig": null,
    "_data_": [
        {},
        {},
        {},
        {},
        {},
        {},
        {},
        {},
        {},
        {}
    ],
    "_height_": {
        "type": "ref",
        "value": "preferred"
    },
    "_indicator_": "none",
    "_left_": {
        "type": "string",
        "value": "0dp"
    },
    "_margin_": [
        0,
        0,
        0,
        0
    ],
    "_orientation_": 2,
    "_padding_": [
        0,
        0,
        0,
        0
    ],
    "_top_": {
        "type": "string",
        "value": "0dp"
    },
    "_width_": {
        "type": "string",
        "value": "100%"
    },
    "autogrowmode": 1,
    "canUpdateUI": true,
    "containerweight": 100,
    "counter": "00",
    "desktop": {
        "_data_": [],
        "rowTemplateId": "h504ecc17bc44665a52ed2cd15050407",
        "rowtemplate": "flxChequeManagementUnSelectedWrapper",
        "sectionHeaderTemplateId": null,
        "selectionBehaviorConfig": null,
        "widgetdatamap": {
            "flxAmount": "flxAmount",
            "flxChequeManagementUnSelectedWrapper": "flxChequeManagementUnSelectedWrapper",
            "flxChequeRange": "flxChequeRange",
            "flxDate": "flxDate",
            "flxDropdown": "flxDropdown",
            "flxLeft": "flxLeft",
            "flxMyChequeRequests": "flxMyChequeRequests",
            "flxReferenceNo": "flxReferenceNo",
            "flxRight": "flxRight",
            "flxSegDisputedTransactionRowWrapper": "flxSegDisputedTransactionRowWrapper",
            "flxSegDisputedTransactionRowWrappers": "flxSegDisputedTransactionRowWrappers",
            "flxStatus": "flxStatus",
            "flxWrapper": "flxWrapper",
            "imgDropDown": "imgDropDown",
            "lblAmount": "lblAmount",
            "lblCurrency": "lblCurrency",
            "lblDate": "lblDate",
            "lblDescription": "lblDescription",
            "lblReferenceNo": "lblReferenceNo",
            "lblSeparator": "lblSeparator",
            "lblSeparator12": "lblSeparator12",
            "lblStatus": "lblStatus"
        }
    },
    "focusedindex": null,
    "focuseditem": null,
    "groupcells": false,
    "hasSections": false,
    "id": "segTransactions",
    "info": null,
    "ipad": {
        "psp": {
            "indicator": "rowselect"
        }
    },
    "iphone": {
        "psp": {
            "indicator": "rowselect"
        }
    },
    "isvisible": true,
    "kuid": "c1b6668dc3ca4f15986fe80fc70f41b0",
    "masterdata": {},
    "mobile": {
        "rowTemplateId": null,
        "rowtemplate": null,
        "sectionHeaderTemplateId": null
    },
    "name": "kony.ui.SegmentedUI2",
    "needpageindicator": true,
    "pageoffdotimage": "pageoffdot.png",
    "pageondotimage": "pageondot.png",
    "paginationconfig": {
        "position": "bottom",
        "vdistance": 1
    },
    "parent": "flxSegmentContainer",
    "pf": "userwidgetmodel",
    "retainselection": false,
    "rowcounter": 0,
    "rowfocusskin": "s9f69e977910472eb44c62ae28c41fe1",
    "rowskin": "sb836d91cb364a16b70a7c6479aba93d",
    "rowtemplate": "flxDisputedChecksSelectedWrapper",
    "screenlevelwidget": false,
    "seccounter": 0,
    "sectionheaderskin": "sdc4ff4ed1584272be2ae69045dfb29d",
    "sectionheadertemplate": "flxSegTransactionHeader",
    "selectedRows": null,
    "selectedState": false,
    "selectedindex": null,
    "selectedindices": null,
    "selecteditems": null,
    "selectedsectionindex": 0,
    "selectionbehavior": "default",
    "separatorrequired": false,
    "showscrollbars": false,
    "swipeContext": {
        "currentPage": 0,
        "imageWidth": 1400,
        "widthRatio": 0
    },
    "viewtype": "tableview",
    "vizProps": {},
    "wType": "Segment",
    "widgetalignment": 5,
    "widgetdatamap": {
        "flxAmount": "flxAmount",
        "flxChequeManagementUnSelectedWrapper": "flxChequeManagementUnSelectedWrapper",
        "flxChequeRange": "flxChequeRange",
        "flxDate": "flxDate",
        "flxDropdown": "flxDropdown",
        "flxLeft": "flxLeft",
        "flxMyChequeRequests": "flxMyChequeRequests",
        "flxReferenceNo": "flxReferenceNo",
        "flxRight": "flxRight",
        "flxSegDisputedTransactionRowWrapper": "flxSegDisputedTransactionRowWrapper",
        "flxSegDisputedTransactionRowWrappers": "flxSegDisputedTransactionRowWrappers",
        "flxStatus": "flxStatus",
        "flxWrapper": "flxWrapper",
        "imgDropDown": "imgDropDown",
        "lblAmount": "lblAmount",
        "lblCurrency": "lblCurrency",
        "lblDate": "lblDate",
        "lblDescription": "lblDescription",
        "lblReferenceNo": "lblReferenceNo",
        "lblSeparator": "lblSeparator",
        "lblSeparator12": "lblSeparator12",
        "lblStatus": "lblStatus"
    },
    "zindex": 1
}