{
    "DNDConfig": null,
    "_height_": {
        "type": "string",
        "value": "15dp"
    },
    "_left_": {
        "type": "string",
        "value": "5dp"
    },
    "_margin_": [
        0,
        0,
        0,
        0
    ],
    "_orientation_": 6,
    "_padding_": [
        0,
        0,
        0,
        0
    ],
    "_percent_": true,
    "_skin_": "sb65c142c0e34c328dfc0d8a0bd562aa",
    "_width_": {
        "type": "string",
        "value": "15dp"
    },
    "allboxes": [],
    "autogrowmode": 0,
    "canUpdateUI": true,
    "centery": {
        "type": "string",
        "value": "50%"
    },
    "children": [],
    "clipbounds": true,
    "containerweight": 100,
    "enablescrolling": true,
    "id": "flxImg1",
    "info": null,
    "iscustomlayout": false,
    "isvisible": true,
    "kuid": "gc4518f21a604379813d0304f6bde10e",
    "layouttype": 2,
    "name": "kony.ui.FlexContainer",
    "parent": "flxHori1",
    "pf": "userwidgetmodel",
    "retaincontentalignment": false,
    "retainflexpositionproperties": false,
    "retainflowhorizontalalignment": false,
    "snapgridsize": 10,
    "snaptogrid": true,
    "wType": "FlexContainer",
    "widgetalignment": 1,
    "zindex": 1
}