{
    "@class": "com.kony.gen.viz.model.component.KVizUserWidget",
    "DNDConfig": null,
    "_children_": [],
    "_height_": {
        "type": "string",
        "value": "121px"
    },
    "_left_": {
        "type": "string",
        "value": "0dp"
    },
    "_margin_": [
        0,
        0,
        0,
        0
    ],
    "_orientation_": 1,
    "_padding_": [
        0,
        0,
        0,
        0
    ],
    "_percent_": true,
    "_skin_": "s24c92fc23b14f5484b693ee9b8a9b35",
    "_top_": {
        "type": "string",
        "value": "0dp"
    },
    "_width_": {
        "type": "string",
        "value": "100%"
    },
    "android": {},
    "androidwearos": {},
    "areflexpropsreferenced": false,
    "autogrowmode": 0,
    "canUpdateUI": true,
    "clipbounds": false,
    "containerweight": 0,
    "dataDiffs": {
        "CopyLabel0a8b12f7002084d": {
            "__events__": {},
            "__info__": {
                "kuid": "a806cf9ceaca484d8583990dffbbeef5",
                "srcKUID": "cb34c29df04d41f58c12dbf5f1600bcf",
                "wType": "Label"
            }
        },
        "CopyLabel0bb648d916e554d": {
            "__events__": {},
            "__info__": {
                "kuid": "h8012245317e404cb6ea833ddbb2bbdb",
                "srcKUID": "c8238c4264144e7391f46d2a256dfbba",
                "wType": "Label"
            }
        },
        "CopyLabel0h9e71b8a76ad44": {
            "__events__": {},
            "__info__": {
                "kuid": "c10f57c03db44ef285de0dfdd7e14fee",
                "srcKUID": "jdc721e253c844bf9eb85dc6aee46d25",
                "wType": "Label"
            }
        },
        "CopyflxSeperator0dfcbfe80de1946": {
            "__events__": {},
            "__info__": {
                "kuid": "b71253f97418452baa93b963bffb66b8",
                "srcKUID": "b7894266c99044dcbcafe5383e83d3db",
                "wType": "FlexContainer"
            }
        },
        "CopyflxUserDetails0b35eb5be884043": {
            "__events__": {},
            "__info__": {
                "kuid": "h40e407d76874c2daad3cdddd4556340",
                "srcKUID": "e9caaacc452a4302b7932fe3f9374adc",
                "wType": "FlexContainer"
            }
        },
        "CopyimgToolTip0i580d9acc07c42": {
            "__events__": {},
            "__info__": {
                "kuid": "j7e8142f2d9d4b3da9fbaef1d94d4da0",
                "srcKUID": "a30ef82b1166480faddbd6e0b99e677d",
                "wType": "Image"
            }
        },
        "FlexContainer0g7f570b54a4d4e": {
            "__events__": {},
            "__info__": {
                "kuid": "beaa878eefb943e2b58159d7d1a70337",
                "srcKUID": "ccc99354aa50423c98c026de8d1c689f",
                "wType": "FlexContainer"
            }
        },
        "Label0dcf00103bdba46": {
            "__events__": {},
            "__info__": {
                "kuid": "ea8aeeb12ad04f4a8bace453edf5de46",
                "srcKUID": "c56fe5fc01b543ad82b37aeb33af56d3",
                "wType": "Label"
            }
        },
        "btnLogout": {
            "__events__": {},
            "__info__": {
                "kuid": "d1b52e6e21f640938327ddbe5622fab9",
                "srcKUID": "dbe084cfcd054a6cb77dabb8ab42f077",
                "wType": "Button"
            }
        },
        "customheadernew": {
            "__events__": {},
            "__info__": {
                "isRoot": true,
                "kuid": "e54cd4f481e04c2a90a0cf9291224e00",
                "srcKUID": "g57ea9eb26d54f30b5f191c7fbd35c51",
                "wType": "FlexContainer"
            }
        },
        "flxAccounts": {
            "__events__": {},
            "__info__": {
                "kuid": "a8215e24292143a6a07412feac18c44d",
                "srcKUID": "e621bc1a1e0848afaf99419615e517b7",
                "wType": "FlexContainer"
            }
        },
        "flxActionsMenu": {
            "__events__": {},
            "__info__": {
                "kuid": "d8e17e30f80d4a6fb5e8127c66c17351",
                "srcKUID": "f5fec7baee6841e7b95c2a53379aeea3",
                "wType": "FlexContainer"
            }
        },
        "flxClose": {
            "__events__": {},
            "__info__": {
                "kuid": "g2c7378cdf734001a3f11a2083955264",
                "srcKUID": "f974fd9704ee48f08006fb2cce1bb1ba",
                "wType": "FlexContainer"
            }
        },
        "flxContextualMenu": {
            "__events__": {},
            "__info__": {
                "kuid": "cd493e181aa742399a3deca23a978467",
                "srcKUID": "j3e46f4bdd64418ba7c405b38661d948",
                "wType": "FlexContainer"
            }
        },
        "flxFeedback": {
            "__events__": {},
            "__info__": {
                "kuid": "d566aefe6cf347d09342cccef060546b",
                "srcKUID": "b8e6354ee0aa42a684fe29b1d98a8db0",
                "wType": "FlexContainer"
            }
        },
        "flxHamburger": {
            "__events__": {},
            "__info__": {
                "kuid": "cffde731441e4a0a8bb53d10fc11ac71",
                "srcKUID": "bb94b45671994d859ad514157efbe460",
                "wType": "FlexContainer"
            },
            "isVisible": false,
            "responsiveData": {
                "b4": {
                    "isVisible": false
                }
            }
        },
        "flxHamburgerBack": {
            "__events__": {},
            "__info__": {
                "kuid": "ac53478d52fa48f180d7ee40475c99b4",
                "srcKUID": "c83e44fca25e458f8c5f4cca992018c1",
                "wType": "FlexContainer"
            }
        },
        "flxHamburgerHeader": {
            "__events__": {},
            "__info__": {
                "kuid": "i285445b4bb044a38cc37513bbba7cd3",
                "srcKUID": "ff14c903773f49fea07675bf1dc6d3aa",
                "wType": "FlexContainer"
            }
        },
        "flxHamburgerMenu": {
            "__events__": {},
            "__info__": {
                "kuid": "cf96e132a7bd4a4fb9725ee15583e24f",
                "srcKUID": "f70dbadab9194d9cab80ed58a380e355",
                "wType": "FlexScrollContainer"
            }
        },
        "flxHelp": {
            "__events__": {},
            "__info__": {
                "kuid": "f27005d5c9c74d9ea2a5e64da1eafc7a",
                "srcKUID": "ab6d787fe40b471184a4baf8371012d8",
                "wType": "FlexContainer"
            }
        },
        "flxImgUser": {
            "__events__": {},
            "__info__": {
                "kuid": "fd23b3e047ad461ab9b32aa7827c0228",
                "srcKUID": "c8bbffe16c9e4322a9c1f2e978bfe397",
                "wType": "FlexContainer"
            }
        },
        "flxLogoAndActions": {
            "__events__": {},
            "__info__": {
                "kuid": "jec3b087432b40cba8dad62688f1f868",
                "srcKUID": "c6cc3d5c40ad4387b5989655ced7897b",
                "wType": "FlexContainer"
            }
        },
        "flxLogoAndActionsWrapper": {
            "__events__": {},
            "__info__": {
                "kuid": "d6f895bba4ed45a0851c710bb7458756",
                "srcKUID": "j19f0c12db9c4a62aca336bb621f2240",
                "wType": "FlexContainer"
            }
        },
        "flxLogout": {
            "__events__": {},
            "__info__": {
                "kuid": "b40893956f584956bcf8c34cdc37c3d1",
                "srcKUID": "b9455970cb324605a7d8d8423734c5d3",
                "wType": "FlexContainer"
            }
        },
        "flxLogoutSeparator": {
            "__events__": {},
            "__info__": {
                "kuid": "j2e267b5f83340f4bad0e347fe43880e",
                "srcKUID": "e307a629419a4a5cb5e6b3dd241e8d33",
                "wType": "FlexContainer"
            }
        },
        "flxLogoutWrapper": {
            "__events__": {},
            "__info__": {
                "kuid": "bacb9d4b9c684812939961625cce1607",
                "srcKUID": "a3a6fced7d8c48c9b292f13fa15f5eb8",
                "wType": "FlexContainer"
            }
        },
        "flxMenu": {
            "__events__": {},
            "__info__": {
                "kuid": "h9c37b5ac74a4ae8a816bdb9816917e1",
                "srcKUID": "c49e3f9c246b4c9eb2037a25593f5949",
                "wType": "FlexContainer"
            }
        },
        "flxMenuContainer": {
            "__events__": {},
            "__info__": {
                "kuid": "a015d19797fa46a7b242bdf6933eb592",
                "srcKUID": "gbe4ab8dec9249a5b1c796d6f8196f51",
                "wType": "FlexContainer"
            }
        },
        "flxMenuItem": {
            "__events__": {},
            "__info__": {
                "kuid": "a614be10687e4bdeb6575ecd80408a78",
                "srcKUID": "b77d75a793c14f2580b76ac27da67298",
                "wType": "FlexContainer"
            }
        },
        "flxMenuItemCollapse": {
            "__events__": {},
            "__info__": {
                "kuid": "i64c2a30041642a9aa315325f72a244a",
                "srcKUID": "b9bab656b60e4d929d0cb26e88d05324",
                "wType": "FlexContainer"
            }
        },
        "flxMenuLeft": {
            "__events__": {},
            "__info__": {
                "kuid": "e397a14fe1524b8e9a79a5063ff5b45b",
                "srcKUID": "ea55f1f130bd498e94b6a730ef3a2340",
                "wType": "FlexContainer"
            }
        },
        "flxMenuRight": {
            "__events__": {},
            "__info__": {
                "kuid": "jfc65a7832fd4adaa07630590d788026",
                "srcKUID": "c7c28fc54fd64c58bc606c327d1900c1",
                "wType": "FlexContainer"
            }
        },
        "flxMenuWrapper": {
            "__events__": {},
            "__info__": {
                "kuid": "c23d2624b7674772add2910b709e78a1",
                "srcKUID": "d0eec1a4de1646d3ab5d92996f569aa7",
                "wType": "FlexContainer"
            }
        },
        "flxMessages": {
            "__events__": {},
            "__info__": {
                "kuid": "acde07eabe5d4bdcb21dbe2cc39ea82c",
                "srcKUID": "fb1a5b65fc494f30bc1e21391fa09491",
                "wType": "FlexContainer"
            }
        },
        "flxMyBills": {
            "__events__": {},
            "__info__": {
                "kuid": "h8ef21d7c41f46a3bb379a15024863ae",
                "srcKUID": "a8bbbc89f77949f4b8140963ab148dce",
                "wType": "FlexContainer"
            }
        },
        "flxNotifications": {
            "__events__": {},
            "__info__": {
                "kuid": "hdd630f539974dad8a1ec82820685faa",
                "srcKUID": "b957e06250dd45ac951449c7bdd6ff51",
                "wType": "FlexContainer"
            }
        },
        "flxPayBills": {
            "__events__": {},
            "__info__": {
                "kuid": "gdba031bce174ed08453663a69cbcd3e",
                "srcKUID": "dfdcb7d977c545c1b7af04aa7b4b38cf",
                "wType": "FlexContainer"
            }
        },
        "flxPayMultipleBeneficiaries": {
            "__events__": {},
            "__info__": {
                "kuid": "g88dc33a216b46978c98a3859532dda5",
                "srcKUID": "f7d21575b7d34f5bac8b07a002b6a76f",
                "wType": "FlexContainer"
            }
        },
        "flxSendMoney": {
            "__events__": {},
            "__info__": {
                "kuid": "j03b2d6124dd436d8b8ab81ec1424c86",
                "srcKUID": "f44ec678efe1449f84d827b60e0ae264",
                "wType": "FlexContainer"
            }
        },
        "flxSeparator1": {
            "__events__": {},
            "__info__": {
                "kuid": "ebe655f2dd7347678dc8aca4b98c3cc0",
                "srcKUID": "b2a298aba680466d8f60575b80e1934e",
                "wType": "FlexContainer"
            }
        },
        "flxSeparatorNew": {
            "__events__": {},
            "__info__": {
                "kuid": "caef011f07f54fc390aecfb8c725c9eb",
                "srcKUID": "ea67f93ff0f94128a71262c9f88d2dbe",
                "wType": "FlexContainer"
            }
        },
        "flxSeperator1": {
            "__events__": {},
            "__info__": {
                "kuid": "f936feae43144730bc86b9072bbec1b3",
                "srcKUID": "db259fcb819a47079972d09155429c2c",
                "wType": "FlexContainer"
            }
        },
        "flxSeperator2": {
            "__events__": {},
            "__info__": {
                "kuid": "fc6641ca67234fd4b45f0c127f990285",
                "srcKUID": "c329b2e37feb4e6384dc95c9e268eedb",
                "wType": "FlexContainer"
            }
        },
        "flxSeperatorMenuItem": {
            "__events__": {},
            "__info__": {
                "kuid": "d97ea480c0ad4b36b208004281c66595",
                "srcKUID": "dc614efa32034c87a72487baa94c4619",
                "wType": "FlexContainer"
            }
        },
        "flxShadowContainer": {
            "__events__": {},
            "__info__": {
                "kuid": "fb71477a453743589bbcd0d4ca782758",
                "srcKUID": "c247bb7332fa47d5bd417b916c7abfec",
                "wType": "FlexContainer"
            },
            "responsiveData": {
                "b3": {
                    "isVisible": false
                }
            }
        },
        "flxSubMenu": {
            "__events__": {},
            "__info__": {
                "kuid": "f10b8e6eb9be46629946a512d86f9642",
                "srcKUID": "dc6c7628618b483a80fcf0bae2dac6db",
                "wType": "FlexContainer"
            }
        },
        "flxSubMenuItem": {
            "__events__": {},
            "__info__": {
                "kuid": "dd4c3ca93d3b4b81aeae305d9f43d45b",
                "srcKUID": "ecc2da3d45e348e0aed2982aed7e9e98",
                "wType": "FlexContainer"
            }
        },
        "flxTransferMoney": {
            "__events__": {},
            "__info__": {
                "kuid": "g6f2df339e8349c09fa366868ea7aaff",
                "srcKUID": "fc180c87f1494b08bd7335e029745f05",
                "wType": "FlexContainer"
            }
        },
        "flxTransfersAndPay": {
            "__events__": {},
            "__info__": {
                "kuid": "e0ab3bb533364a179b0d8045d01865a7",
                "srcKUID": "je4acb4201274a92bebc604f30a7947a",
                "wType": "FlexContainer"
            }
        },
        "flxUser": {
            "__events__": {},
            "__info__": {
                "kuid": "e0e80d92934d4f7eaa27e143b89642c5",
                "srcKUID": "g4f3d73c7f364988900a280daf5753d8",
                "wType": "FlexContainer"
            }
        },
        "flxUserActions": {
            "__events__": {},
            "__info__": {
                "kuid": "a52b1725843845308bc1ad354e0dfa1b",
                "srcKUID": "c82435ddffbe4a299e1b432baa97fe80",
                "wType": "FlexContainer"
            }
        },
        "flxUserActionsWrapper": {
            "__events__": {},
            "__info__": {
                "kuid": "d1885fc27d8347c0b9af63cecf299177",
                "srcKUID": "bfea9c9b15964d019ae9a28ded0b7d9d",
                "wType": "FlexContainer"
            }
        },
        "flxVerticalSeperator3": {
            "__events__": {},
            "__info__": {
                "kuid": "c8bc747e97014e8d874ea0ec3fd20659",
                "srcKUID": "e3cc9979f7a04363b4152d09c867783a",
                "wType": "FlexContainer"
            }
        },
        "flxWarning": {
            "__events__": {},
            "__info__": {
                "kuid": "bf52032b10194346861b72806e9fc4e9",
                "srcKUID": "c7ae9fe97da545ebad3bd6254cb34391",
                "wType": "FlexContainer"
            }
        },
        "flxWireMoney": {
            "__events__": {},
            "__info__": {
                "kuid": "f5cb84ff4dfc48a3876a06bbf242abc2",
                "srcKUID": "a7e3790fa138476e9b408a269f31269d",
                "wType": "FlexContainer"
            }
        },
        "flxverseperator2": {
            "__events__": {},
            "__info__": {
                "kuid": "d292c36746cd4281a939d5490553352f",
                "srcKUID": "b5adbb16a78e40f4aa5b53cf5caa919d",
                "wType": "FlexContainer"
            }
        },
        "imgClose": {
            "__events__": {},
            "__info__": {
                "kuid": "cc905b55a86443df9c7b721b09f2cd92",
                "srcKUID": "f0059293a90844408fdc2a3c558f25b9",
                "wType": "Image"
            },
            "src": "menu_close_white.png"
        },
        "imgCollapseMenuItem": {
            "__events__": {},
            "__info__": {
                "kuid": "e8b6c0e335414435b9df5f9f3d55fd5c",
                "srcKUID": "ba746db189ad42989176b888b25ae78b",
                "wType": "Image"
            }
        },
        "imgKony": {
            "__events__": {},
            "__info__": {
                "kuid": "f3f393ef87844631ac05fc1b106b7a07",
                "srcKUID": "c55a5df1953849bc921a9a84a2cf5e70",
                "wType": "Image"
            },
            "src": "kony_logo.png"
        },
        "imgKonyHamburger": {
            "__events__": {},
            "__info__": {
                "kuid": "d709cabd01e145708b0854034d4010a6",
                "srcKUID": "b77eae507bff4b2d91fbf7670574d59e",
                "wType": "Image"
            },
            "src": "kony_logo_white.png"
        },
        "imgLblTransfers": {
            "__events__": {},
            "__info__": {
                "kuid": "e1fb665a06b946a298498c504b64886f",
                "srcKUID": "ffe510df4f16410e92dc6721f851a592",
                "wType": "Label"
            }
        },
        "imgLogout": {
            "__events__": {},
            "__info__": {
                "kuid": "hd28b1c2f9d7411fab0fcb9e42776ce7",
                "srcKUID": "d67b5f46dcd44029b4cba5d652ef4e4a",
                "wType": "Image"
            },
            "src": "logout.png"
        },
        "imgMenu": {
            "__events__": {},
            "__info__": {
                "kuid": "b614de99cd414ba1a9045a40061424c5",
                "srcKUID": "fc4d7ba517c748f08b831479a140671f",
                "wType": "Image"
            },
            "src": "menu_icon.png"
        },
        "imgMessages": {
            "__events__": {},
            "__info__": {
                "kuid": "i795b02ffbbb47eaafd2caf508c47801",
                "srcKUID": "f1f230dd87ef4b47b5974acaf9e328d5",
                "wType": "Label"
            }
        },
        "imgNotifications": {
            "__events__": {},
            "__info__": {
                "kuid": "e08c923ab37b4859b738c31d2d5bb447",
                "srcKUID": "a6e8c4a6887349caac366cd06a1a61c7",
                "wType": "Image"
            },
            "src": "notification_flag.png"
        },
        "imgToolTip": {
            "__events__": {},
            "__info__": {
                "kuid": "d59f569395914ac19a623ab2ddb0aa45",
                "srcKUID": "j6d5d0d57c4d4c51bb3c07fc94674e0b",
                "wType": "Image"
            }
        },
        "imgUser": {
            "__events__": {},
            "__info__": {
                "kuid": "f74639e97d474d5bb2782a4443764f92",
                "srcKUID": "c653f12789ff45178bc1061b44158c51",
                "wType": "Image"
            }
        },
        "imgWarning": {
            "__events__": {},
            "__info__": {
                "kuid": "ebd6974371a6427f8f58cc71e5829e06",
                "srcKUID": "a008b61365884da1aeefa554430f6343",
                "wType": "Image"
            }
        },
        "lblAccounts": {
            "__events__": {},
            "__info__": {
                "kuid": "aa7dee6b00784f81b4bfce5cf38a3945",
                "srcKUID": "a44ff4b384ce41fbbd285f88cde71bc7",
                "wType": "Label"
            }
        },
        "lblFeedback": {
            "__events__": {},
            "__info__": {
                "kuid": "i58b96f4fa7b4b9ea160c43ad5785efb",
                "srcKUID": "f221b6bbddac4ec097577e0e2abbf72a",
                "wType": "Label"
            }
        },
        "lblHeaderMobile": {
            "__events__": {},
            "__info__": {
                "kuid": "ddf95d6589a042d795693d738181f152",
                "srcKUID": "fc0477569a7346b79ef7b5d61246a700",
                "wType": "Label"
            },
            "i18n_text": null,
            "responsiveData": {
                "b2": {},
                "b3": {
                    "text": "Profile Settings"
                },
                "b4": {}
            },
            "text": ""
        },
        "lblHelp": {
            "__events__": {},
            "__info__": {
                "kuid": "j15bddab2aea456cb5e2a904dc2c2dcd",
                "srcKUID": "fbd3358a503c410282a41bea6a18f47d",
                "wType": "Label"
            }
        },
        "lblImageLogout": {
            "__events__": {},
            "__info__": {
                "kuid": "a3f82d61eab8422c9acb176e9f1cd52b",
                "srcKUID": "cf90f7d15b31420dabef06dda7f90c2b",
                "wType": "Label"
            }
        },
        "lblLogout": {
            "__events__": {},
            "__info__": {
                "kuid": "c6f9141ead55496a9e35ccbf2abf826a",
                "srcKUID": "e2654abf270340819750f9f33e4dbfc3",
                "wType": "Label"
            }
        },
        "lblLogoutIcon": {
            "__events__": {},
            "__info__": {
                "kuid": "a48bfe3a08304724bb093af56a28b4f1",
                "srcKUID": "f7201d67d487488f8b79f6de86dac851",
                "wType": "Label"
            }
        },
        "lblMenuItemIcon": {
            "__events__": {},
            "__info__": {
                "kuid": "fb41e598f28a4850aace2248fed50bea",
                "srcKUID": "b0f1d3eb6b5c4edfb845c0cadd9a65b2",
                "wType": "Label"
            }
        },
        "lblMenuItemTitle": {
            "__events__": {},
            "__info__": {
                "kuid": "i25dc36360e944989068cef6c78b6d6a",
                "srcKUID": "h5445b09c22d41dba82780d50a162e5d",
                "wType": "Label"
            }
        },
        "lblMyAccounts": {
            "__events__": {},
            "__info__": {
                "kuid": "if8d9b31203e4e1692dc6a3c2fb91633",
                "srcKUID": "a7ae02bf520e467bad62d17620dbcd9c",
                "wType": "Label"
            }
        },
        "lblMyBills": {
            "__events__": {},
            "__info__": {
                "kuid": "e1407d896ece4371a5b30264a9b259cc",
                "srcKUID": "f07f6e1e108847c893514c948793123d",
                "wType": "Label"
            },
            "isVisible": true,
            "responsiveData": {
                "b3": {
                    "isVisible": false
                }
            }
        },
        "lblName": {
            "__events__": {},
            "__info__": {
                "kuid": "cc86840b1ccc43cbb3d44ce97288b2d9",
                "srcKUID": "df2a7db2a13842f8b69f45d798f91ca4",
                "wType": "Label"
            }
        },
        "lblNewMessages": {
            "__events__": {},
            "__info__": {
                "kuid": "e55fd27b58574fe1b52dd763a44bd0fe",
                "srcKUID": "b0381d20648a4eed9bbc9d20d2705f0f",
                "wType": "Label"
            }
        },
        "lblNewNotifications": {
            "__events__": {},
            "__info__": {
                "kuid": "cf79ce6ec5924f409136c9c286e4d75b",
                "srcKUID": "e390473ef6224482b645ddbbabb4246e",
                "wType": "Label"
            }
        },
        "lblNotifications": {
            "__events__": {},
            "__info__": {
                "kuid": "g9a695229a5f4c34aac2067e182ac8cb",
                "srcKUID": "i7fff3f628284b4ab5d010088e9dada9",
                "wType": "Label"
            }
        },
        "lblPayMultipleBeneficiaries": {
            "__events__": {},
            "__info__": {
                "kuid": "e213165999a64465810df538501965ca",
                "srcKUID": "ib0cb6bd824744998bee9f5e6612b486",
                "wType": "Label"
            }
        },
        "lblTransferAndPay": {
            "__events__": {},
            "__info__": {
                "kuid": "cda09c84c5b74e108978e34f5ef90c17",
                "srcKUID": "b16c43dc82314d26bd801952202150c1",
                "wType": "Label"
            }
        },
        "lblUserEmail": {
            "__events__": {},
            "__info__": {
                "kuid": "a16299d0b9ec40a69953ce720d340a6b",
                "srcKUID": "j0626d5e09c04c8e82eefdb4d6a5a20b",
                "wType": "RichText"
            }
        },
        "rtxWarning": {
            "__events__": {},
            "__info__": {
                "kuid": "d162d3485de246e2878b662d744a10b5",
                "srcKUID": "bcfca1ce25a742b4a4fe3ffb534a8743",
                "wType": "RichText"
            }
        },
        "segUserActions": {
            "__events__": {},
            "__info__": {
                "kuid": "gfd66e34413a4a1ea8d3f0bd93b55093",
                "srcKUID": "d628530db75f48cfaf1e94b7e138808a",
                "wType": "Segment"
            }
        }
    },
    "desktopweb": {},
    "enablescrolling": true,
    "id": "customheadernew",
    "info": null,
    "ipad": {},
    "iphone": {},
    "isdatareferenced": false,
    "isvisible": true,
    "kiosk": {},
    "kuid": "e54cd4f481e04c2a90a0cf9291224e00",
    "layouttype": 2,
    "masterType": 0,
    "name": "kony.ui.UserWidgetInstance",
    "parent": "flxHeader",
    "pf": "frmAccountAlertsEdit",
    "responsiveData": {},
    "snapgridsize": 10,
    "snaptogrid": true,
    "sourceUserWidget": "g57ea9eb26d54f30b5f191c7fbd35c51",
    "spa": {},
    "spaan": {},
    "spaandroidtablet": {},
    "spabb": {},
    "spaip": {},
    "spaipad": {},
    "spamobile": {},
    "spatablet": {},
    "spawindowstablet": {},
    "spawinphone8": {},
    "tabrcandroid": {},
    "vizProps": {
        "hidewidgethierarchy": false
    },
    "wType": "UserWidgetInstance",
    "windows10": {},
    "windows8": {},
    "winphone10": {},
    "winphone8": {},
    "zindex": 1000
}