{
    "@class": "com.kony.gen.viz.model.component.KVizLabel",
    "DNDConfig": null,
    "_height_": {
        "type": "ref",
        "value": "preferred"
    },
    "_left_": {
        "type": "string",
        "value": "2.29%"
    },
    "_margin_": [
        1,
        1,
        1,
        1
    ],
    "_padding_": [
        0,
        0,
        0,
        0
    ],
    "_skin_": "s10a0c62c2af4452bd7132e27e8f5a49",
    "_text_": "Existing Password : ",
    "_top_": {
        "type": "string",
        "value": "30dp"
    },
    "_width_": {
        "type": "ref",
        "value": "preferred"
    },
    "_wrapping_": 2,
    "accessibilityconfig": {
        "a11yLabel": "Existing Password:"
    },
    "android": {
        "textStyle": {
            "letterSpacing": 0,
            "strikeThrough": false
        }
    },
    "canUpdateUI": true,
    "containerweight": 100,
    "contentalignment": 4,
    "id": "lblExistingPassword",
    "info": null,
    "ipad": {
        "psp": {
            "wrapping": 2
        }
    },
    "iphone": {
        "psp": {
            "wrapping": 2
        }
    },
    "isvisible": true,
    "kuid": "f66dc25d96b44ddd869b32a18ed1fc08",
    "name": "kony.ui.Label",
    "parent": "flxExistingPassword",
    "pf": "userwidgetmodel",
    "texti18n": "i18n.ProfileManagement.ExistingPassword",
    "tooltip": "",
    "wType": "Label",
    "zindex": 1
}