{
    "@class": "com.kony.gen.viz.model.component.KVizButton",
    "DNDConfig": null,
    "_height_": {
        "type": "string",
        "value": "50dp"
    },
    "_left_": {
        "type": "number",
        "value": ""
    },
    "_margin_": [
        6,
        6,
        6,
        6
    ],
    "_padding_": [
        0,
        0,
        0,
        0
    ],
    "_right_": {
        "type": "string",
        "value": "23.18%"
    },
    "_skin_": "sbf2a0f68cc944cd9e17675489e4f03d",
    "_text_": "",
    "_top_": {
        "type": "number",
        "value": ""
    },
    "_width_": {
        "type": "string",
        "value": "21.40%"
    },
    "accessibilityconfig": {
        "a11yLabel": "Modify"
    },
    "canUpdateUI": true,
    "centerx": {
        "type": "number",
        "value": ""
    },
    "centery": {
        "type": "string",
        "value": "50%"
    },
    "containerweight": 100,
    "contentalignment": 5,
    "desktopweb": {
        "psp": {
            "hoverSkin": "s41b4477fcac4dc7971801c2ef8a5a09"
        }
    },
    "disabledSkins": {},
    "displaytext": true,
    "focusskin": "s3ca713a4e3748db9e33b8a9dea72933",
    "id": "btnModify",
    "info": null,
    "isvisible": true,
    "kuid": "b2bd90173998455dbbefde69730b1eb7",
    "name": "kony.ui.Button",
    "parent": "flxConfirmButtons",
    "pf": "userwidgetmodel",
    "responsiveData": {
        "b1": {
            "height": {
                "type": "string",
                "value": "40px"
            },
            "left": {
                "type": "string",
                "value": ""
            },
            "right": {
                "type": "string",
                "value": "270px"
            },
            "skin": "s434743e49c446699565893e4974ec52",
            "width": {
                "type": "string",
                "value": "250px"
            }
        },
        "b2": {
            "centerY": {
                "type": "string",
                "value": ""
            },
            "height": {
                "type": "string",
                "value": "40dp"
            },
            "right": {
                "type": "string",
                "value": "270px"
            },
            "skin": "s434743e49c446699565893e4974ec52",
            "top": {
                "type": "string",
                "value": "0dp"
            },
            "width": {
                "type": "string",
                "value": "250px"
            }
        },
        "b3": {
            "centerX": {
                "type": "string",
                "value": "50%"
            },
            "centerY": {
                "type": "string",
                "value": ""
            },
            "height": {
                "type": "string",
                "value": "40dp"
            },
            "left": {
                "type": "string",
                "value": "20dp"
            },
            "right": {
                "type": "string",
                "value": "20dp"
            },
            "skin": "s434743e49c446699565893e4974ec52",
            "top": {
                "type": "string",
                "value": "60dp"
            },
            "width": {
                "type": "string",
                "value": "93.75%"
            }
        }
    },
    "texti18n": "i18n.ViewStatements.GoToAccountSummary",
    "tooltip": "MODIFY",
    "wType": "Button",
    "zindex": 1
}