{
    "DNDConfig": null,
    "_height_": {
        "type": "string",
        "value": "220dp"
    },
    "_left_": {
        "type": "string",
        "value": "112dp"
    },
    "_margin_": [
        0,
        0,
        0,
        0
    ],
    "_orientation_": 6,
    "_padding_": [
        0,
        0,
        0,
        0
    ],
    "_percent_": true,
    "_skin_": "s24c92fc23b14f5484b693ee9b8a9b35",
    "_top_": {
        "type": "string",
        "value": "0dp"
    },
    "_width_": {
        "type": "string",
        "value": "100%"
    },
    "allboxes": [],
    "canUpdateUI": true,
    "children": [
        "lblAccountTitleM",
        "lblAccountValueM",
        "flxCancelAccountM"
    ],
    "clipbounds": true,
    "containerweight": 100,
    "enablescrolling": true,
    "id": "flxAccountWrapper",
    "info": null,
    "iscustomlayout": false,
    "isvisible": true,
    "kuid": "b80e27efb5d3483ca9c3c0f128d65ec8",
    "layouttype": 2,
    "name": "kony.ui.FlexContainer",
    "parent": "flxSearchItemsMobile",
    "pf": "userwidgetmodel",
    "responsiveData": {
        "b3": {
            "height": {
                "type": "string",
                "value": "22dp"
            },
            "layoutType": 3,
            "left": {
                "type": "string",
                "value": "0dp"
            },
            "top": {
                "type": "string",
                "value": "10dp"
            }
        }
    },
    "retaincontentalignment": false,
    "retainflexpositionproperties": false,
    "retainflowhorizontalalignment": false,
    "snapgridsize": 10,
    "snaptogrid": true,
    "wType": "FlexContainer",
    "widgetalignment": 1,
    "zindex": 1
}