{
    "@class": "com.kony.gen.viz.model.component.KVizImage2",
    "DNDConfig": null,
    "_base64_": null,
    "_height_": {
        "type": "string",
        "value": "12dp"
    },
    "_left_": {
        "type": "string",
        "value": "9dp"
    },
    "_margin_": [
        0,
        0,
        0,
        0
    ],
    "_padding_": [
        0,
        0,
        0,
        0
    ],
    "_skin_": "s78a5f26c9f14cec9ebed1bb46098f80",
    "_src_": "arrow_down.png",
    "_top_": {
        "type": "string",
        "value": "11dp"
    },
    "_width_": {
        "type": "string",
        "value": "12dp"
    },
    "accessibilityconfig": {
        "a11yLabel": "Section Dropdown",
        "a11yValue": ""
    },
    "canUpdateUI": true,
    "centerx": {
        "type": "string",
        "value": "50%"
    },
    "centery": {
        "type": "string",
        "value": "50%"
    },
    "containerId": true,
    "containerweight": 100,
    "id": "imgCollapse",
    "imagescalemode": 1,
    "info": null,
    "invokedProperty": "src",
    "isvisible": true,
    "kuid": "a65203300419465daa2f988b7fc77c1b",
    "name": "kony.ui.Image2",
    "parent": "flxCollapse",
    "pf": "segMyCardsCollapsedNew",
    "srcType": 1,
    "wType": "Image",
    "widgetalignment": 5,
    "zindex": 1
}