{
    "@class": "com.kony.gen.viz.model.component.KVizUserWidget",
    "DNDConfig": null,
    "_bottom_": {
        "type": "string",
        "value": ""
    },
    "_children_": [],
    "_height_": {
        "type": "ref",
        "value": "preferred"
    },
    "_left_": {
        "type": "string",
        "value": ""
    },
    "_margin_": [
        0,
        0,
        0,
        0
    ],
    "_orientation_": 1,
    "_padding_": [
        0,
        0,
        0,
        0
    ],
    "_percent_": true,
    "_skin_": "s24c92fc23b14f5484b693ee9b8a9b35",
    "_top_": {
        "type": "string",
        "value": "0dp"
    },
    "_width_": {
        "type": "ref",
        "value": "preferred"
    },
    "areflexpropsreferenced": false,
    "autogrowmode": 1,
    "canUpdateUI": true,
    "clipbounds": false,
    "containerweight": 0,
    "dataDiffs": {
        "MobileCustomDropdown": {
            "__events__": {},
            "__info__": {
                "kuid": "a60e59d9c2eb499d8a9a611628e7dd6c",
                "srcKUID": "jeb8c613aa99488aafc7ce36f505b47d",
                "wType": "FlexContainer"
            },
            "isVisible": false,
            "responsiveData": {
                "b3": {
                    "isVisible": false
                }
            }
        },
        "MobileCustomDropdown.CopyflxTimePeriodSeparator0iad4443c80964c": {
            "__events__": {},
            "__info__": {
                "kuid": "hc70f51d50b149038763a004e2f02040",
                "srcKUID": "e50bdbf23ef143a1abe7031c4cf6855c",
                "wType": "FlexContainer"
            }
        },
        "MobileCustomDropdown.btnApplyFilter": {
            "__events__": {},
            "__info__": {
                "kuid": "cbea7919547c490fae1634dd5c4c8d06",
                "srcKUID": "f2eeff0740a44e82adc27d9433f9ecb3",
                "wType": "Button"
            }
        },
        "MobileCustomDropdown.btnCancelFilter": {
            "__events__": {},
            "__info__": {
                "kuid": "dc7c78c01e084f16992bec3454f0e3f6",
                "srcKUID": "j6bfc4bd9fbf404ea9660c7610e2f11f",
                "wType": "Button"
            }
        },
        "MobileCustomDropdown.flxAll": {
            "__events__": {},
            "__info__": {
                "kuid": "b7492903fae04809b6c038afe0556796",
                "srcKUID": "b422239db00c4199a2b7e38d72b925c9",
                "wType": "FlexContainer"
            }
        },
        "MobileCustomDropdown.flxApprovalTypeSeparator": {
            "__events__": {},
            "__info__": {
                "kuid": "ca7eb17eb929471fa273e322e2a2bb63",
                "srcKUID": "a91b31ce12a5436abe1b3eeedd845f0e",
                "wType": "FlexContainer"
            }
        },
        "MobileCustomDropdown.flxApproveType": {
            "__events__": {},
            "__info__": {
                "kuid": "f8c8af7a6b3b4056921c03136d54b811",
                "srcKUID": "f4727e223c4b4410ae0e71be0d0405c1",
                "wType": "FlexContainer"
            }
        },
        "MobileCustomDropdown.flxButtons": {
            "__events__": {},
            "__info__": {
                "kuid": "e28a9e928a404565acd4a4a1c3f00a76",
                "srcKUID": "g48cc6e8c7704b90aba6f5405ffb56fb",
                "wType": "FlexContainer"
            }
        },
        "MobileCustomDropdown.flxCurrencyBody": {
            "__events__": {},
            "__info__": {
                "kuid": "cec8a7c8a9704c17a9e1a869e51ec9e1",
                "srcKUID": "faaabd33420a4f42bffc4f2bab93171f",
                "wType": "FlexContainer"
            }
        },
        "MobileCustomDropdown.flxCurrencyExpand": {
            "__events__": {},
            "__info__": {
                "kuid": "db532025386641398b5cecd5426ead4c",
                "srcKUID": "ie61553e4f6141a5b5bd9d2399d6fafc",
                "wType": "FlexContainer"
            }
        },
        "MobileCustomDropdown.flxCurrencyHeader": {
            "__events__": {},
            "__info__": {
                "kuid": "g1b9767c5c994b88939edfd34845e9a8",
                "srcKUID": "ec9e59e0e4624513b030cd6fec7d244c",
                "wType": "FlexContainer"
            }
        },
        "MobileCustomDropdown.flxCurrencyTitle": {
            "__events__": {},
            "__info__": {
                "kuid": "d1d0455c4cba4de2971987f4520d67d2",
                "srcKUID": "a381699f3015438d86cbefa89d7033b3",
                "wType": "FlexContainer"
            }
        },
        "MobileCustomDropdown.flxDropdown": {
            "__events__": {},
            "__info__": {
                "kuid": "cbe1586d68a848f28139044c28b95743",
                "srcKUID": "bff6f39a998a4febbcda6d509b1a7882",
                "wType": "FlexContainer"
            }
        },
        "MobileCustomDropdown.flxDropdownCurrency": {
            "__events__": {},
            "__info__": {
                "kuid": "d3309609bfe74c47875dd6a06f20b820",
                "srcKUID": "g08430c5bb224bdc9e05fdbf3d4b490d",
                "wType": "FlexContainer"
            }
        },
        "MobileCustomDropdown.flxDropdownImage": {
            "__events__": {},
            "__info__": {
                "kuid": "c73e39bd78054c4a973013500b1f64ed",
                "srcKUID": "b86b9b12b45e40f79c7e9581f47773cd",
                "wType": "FlexContainer"
            }
        },
        "MobileCustomDropdown.flxFilter": {
            "__events__": {},
            "__info__": {
                "kuid": "d756a6160cf14e3f8e5af0b4d231d8c9",
                "srcKUID": "i5bcc6dc0e9e435bbfb2e0e8741d771c",
                "wType": "FlexContainer"
            }
        },
        "MobileCustomDropdown.flxImage": {
            "__events__": {},
            "__info__": {
                "kuid": "j01dc622323e4483a0f8aee5ee5d290f",
                "srcKUID": "cd00e6fa98584cd6899e5fa23884fa55",
                "wType": "FlexContainer"
            }
        },
        "MobileCustomDropdown.flxIphoneDropdown": {
            "__events__": {},
            "__info__": {
                "kuid": "c43bc73f04b8416283649bdb0eea7be4",
                "srcKUID": "d5982645c62d4eb9bb7b1be5f09d419d",
                "wType": "FlexContainer"
            },
            "isVisible": true,
            "responsiveData": {
                "b1": {
                    "isVisible": false
                },
                "b2": {
                    "isVisible": false
                },
                "b3": {
                    "isVisible": false
                },
                "b4": {
                    "isVisible": false
                }
            }
        },
        "MobileCustomDropdown.flxProcessingType": {
            "__events__": {},
            "__info__": {
                "kuid": "a7493f0e6bb045e4a092711e33aa68bc",
                "srcKUID": "hcede7a5a69f4aae82c2f83239a774a3",
                "wType": "FlexContainer"
            }
        },
        "MobileCustomDropdown.flxProcessingTypeBottomSeparator": {
            "__events__": {},
            "__info__": {
                "kuid": "e3f6895ed7bc42d794a93490aa0da36d",
                "srcKUID": "ba6cb0b40e8b49848c42bc1f0c06f554",
                "wType": "FlexContainer"
            }
        },
        "MobileCustomDropdown.flxProcessingTypeDropdownImage": {
            "__events__": {},
            "__info__": {
                "kuid": "e06678b1e1ac4f0b802d406b247341c6",
                "srcKUID": "h37c8e6d5ddf423abbf2397c43866f80",
                "wType": "FlexContainer"
            }
        },
        "MobileCustomDropdown.flxProcessingTypeHeaderContent": {
            "__events__": {},
            "__info__": {
                "kuid": "e23e087c1b564cf6bb5d792c87f80147",
                "srcKUID": "d5a1e2be9fe44f268b6345b9c3c9a9f5",
                "wType": "FlexContainer"
            }
        },
        "MobileCustomDropdown.flxProcessingTypeHeaderDropdown": {
            "__events__": {},
            "__info__": {
                "kuid": "e15cc71500884f4fba4022b1a4f9d222",
                "srcKUID": "b90d386976ac466ea40a114edd44dd24",
                "wType": "FlexContainer"
            }
        },
        "MobileCustomDropdown.flxProcessingTypeTopSeparator": {
            "__events__": {},
            "__info__": {
                "kuid": "ff0db1fc183247b0a4e6dc050a420b9e",
                "srcKUID": "ed2b32ab39484b9da85c29a5f1623ac2",
                "wType": "FlexContainer"
            }
        },
        "MobileCustomDropdown.flxSeperatorCurrency": {
            "__events__": {},
            "__info__": {
                "kuid": "i004f0494b77410aaca096d0330fd10a",
                "srcKUID": "d82e4a031c334985b92551f32ab0164b",
                "wType": "FlexContainer"
            }
        },
        "MobileCustomDropdown.flxSeperatorToa": {
            "__events__": {},
            "__info__": {
                "kuid": "cfd632ebd45949fd8a5f44e448c760da",
                "srcKUID": "hef64ae754894a54871be771155fa053",
                "wType": "FlexContainer"
            }
        },
        "MobileCustomDropdown.flxSeperatorToaTitle": {
            "__events__": {},
            "__info__": {
                "kuid": "cc6218bb83f24d069dcefa8bf907238c",
                "srcKUID": "dda02d6602f44ebb9c96cc4c0277eb3f",
                "wType": "FlexContainer"
            }
        },
        "MobileCustomDropdown.flxStatus": {
            "__events__": {},
            "__info__": {
                "kuid": "a32c193696254acfa76a59727f723294",
                "srcKUID": "c29dc27e430d44098eaeb1b4393fe0bf",
                "wType": "FlexContainer"
            }
        },
        "MobileCustomDropdown.flxTimePeriod": {
            "__events__": {},
            "__info__": {
                "kuid": "c858607ec5d64af882afd05be7ad78e7",
                "srcKUID": "ge890363b2fa410dbe464016de4532f8",
                "wType": "FlexContainer"
            }
        },
        "MobileCustomDropdown.flxTimePeriodDropdownImage": {
            "__events__": {},
            "__info__": {
                "kuid": "f94869860b59497abbf2a29d4f64ec07",
                "srcKUID": "db80693440da4dc99b9fbcd8e365cfd2",
                "wType": "FlexContainer"
            }
        },
        "MobileCustomDropdown.flxTimePeriodHeader": {
            "__events__": {},
            "__info__": {
                "kuid": "j1c1616ff6db4312bfb69a3fdf5ab552",
                "srcKUID": "cb6d78fb67704d09b78fc2910d3d47c9",
                "wType": "FlexContainer"
            }
        },
        "MobileCustomDropdown.flxTimePeriodHeaderDropdown": {
            "__events__": {},
            "__info__": {
                "kuid": "e1628af30f394d22bebe9f5fbe388960",
                "srcKUID": "j9ce92d6b2a24172b411b9f38bb4bff0",
                "wType": "FlexContainer"
            }
        },
        "MobileCustomDropdown.flxTimePeriodSeparator": {
            "__events__": {},
            "__info__": {
                "kuid": "c91882aac3e24b5ab8e24d1523afca18",
                "srcKUID": "gcabe4231d6c4ee0960731cc91d064d7",
                "wType": "FlexContainer"
            }
        },
        "MobileCustomDropdown.flxTimeperiodBody": {
            "__events__": {},
            "__info__": {
                "kuid": "d714c7dc759a451e901505a5eeb4774b",
                "srcKUID": "j971794a32224bafa0ca6060c3a13e27",
                "wType": "FlexContainer"
            }
        },
        "MobileCustomDropdown.flxTimeperiodHeaderContent": {
            "__events__": {},
            "__info__": {
                "kuid": "h914c49ca62b4513879ed335b2ae4c3e",
                "srcKUID": "e068f773e82e437084acead05f62b291",
                "wType": "FlexContainer"
            }
        },
        "MobileCustomDropdown.flxToaBody": {
            "__events__": {},
            "__info__": {
                "kuid": "b0d80f6ea9e146a989468b682e0727a3",
                "srcKUID": "da0fe9c1383c4162bd7e363984376967",
                "wType": "FlexContainer"
            }
        },
        "MobileCustomDropdown.flxToaHeader": {
            "__events__": {},
            "__info__": {
                "kuid": "b06fb4dc90cf46cfa123d573e12cb08c",
                "srcKUID": "j56092107afa474eba0f47c785202779",
                "wType": "FlexContainer"
            }
        },
        "MobileCustomDropdown.flxToaHeaderTitle": {
            "__events__": {},
            "__info__": {
                "kuid": "h0b865ccfcc44cc6b1b64a7dbe9a4944",
                "srcKUID": "g735658b57e641b2bdb76250c4aa2b1c",
                "wType": "FlexContainer"
            }
        },
        "MobileCustomDropdown.flxTypeOfAccountsExpand": {
            "__events__": {},
            "__info__": {
                "kuid": "e8d252a40409472dbb44f340829125fa",
                "srcKUID": "j1a3086165074e7f89491c109f073869",
                "wType": "FlexContainer"
            }
        },
        "MobileCustomDropdown.flxprocessingTypeBody": {
            "__events__": {},
            "__info__": {
                "kuid": "i98cb97d7e6d4702a12c74f943682a83",
                "srcKUID": "be96e2f6e3724bf79a2b991a9fee069a",
                "wType": "FlexContainer"
            }
        },
        "MobileCustomDropdown.flxprocessingTypeHeader": {
            "__events__": {},
            "__info__": {
                "kuid": "gd18202f98d54428ae5168425d3253d7",
                "srcKUID": "ca61009b2afe4426b01964503590bdad",
                "wType": "FlexContainer"
            }
        },
        "MobileCustomDropdown.imgDropdown": {
            "__events__": {},
            "__info__": {
                "kuid": "e40ca70a8b13484bbd25efb5917e149a",
                "srcKUID": "a27dc5d847e14c93b1e719fe64d79d1a",
                "wType": "Image"
            }
        },
        "MobileCustomDropdown.imgDropdownTimeperiod": {
            "__events__": {},
            "__info__": {
                "kuid": "bae1a1012fbe4c7b9fbec3b8f3b5e1bc",
                "srcKUID": "e78a7a9f1710438cb893022efc61203f",
                "wType": "Label"
            }
        },
        "MobileCustomDropdown.imgDropdownprocessingType": {
            "__events__": {},
            "__info__": {
                "kuid": "i21192015db14ba2b3aa1eb9fcfdb2cb",
                "srcKUID": "f34077d626bd48a9888e24e3f008d5b5",
                "wType": "Label"
            }
        },
        "MobileCustomDropdown.lblAll": {
            "__events__": {},
            "__info__": {
                "kuid": "jcabe069e9b44d21a9f1d65a6dc00295",
                "srcKUID": "a3e804e5c94c4a9c9f0b74a29f317fae",
                "wType": "Label"
            }
        },
        "MobileCustomDropdown.lblAllValue": {
            "__events__": {},
            "__info__": {
                "kuid": "gc97dbf4d4e0486fb628b823956edfb1",
                "srcKUID": "c926efe57efe436baf2da96ca421a3d3",
                "wType": "Label"
            }
        },
        "MobileCustomDropdown.lblCurrencyType": {
            "__events__": {},
            "__info__": {
                "kuid": "e3db35512a9b4e9ab0f6a7a0260262b6",
                "srcKUID": "b3a37ab7a42c478ea68c248f999afecd",
                "wType": "Label"
            }
        },
        "MobileCustomDropdown.lblFilterCount": {
            "__events__": {},
            "__info__": {
                "kuid": "a0e388678ee34400a309ffdcc59c3c8c",
                "srcKUID": "d9a86f22dfd84bc2bffd47375d6db2a0",
                "wType": "Label"
            }
        },
        "MobileCustomDropdown.lblImage": {
            "__events__": {},
            "__info__": {
                "kuid": "b0d0a8b36cd34ca2b27a5070a013d97f",
                "srcKUID": "i5b21ca5b383407bbc8d6fcafba17aee",
                "wType": "Label"
            }
        },
        "MobileCustomDropdown.lblImageCurrency": {
            "__events__": {},
            "__info__": {
                "kuid": "d1b4efb424964014bfbdc1cd56fb68f6",
                "srcKUID": "d3211b72cba342ad899d4c051821fb7c",
                "wType": "Label"
            }
        },
        "MobileCustomDropdown.lblProcessingTypeContent": {
            "__events__": {},
            "__info__": {
                "kuid": "e5f74027feb54da2919d8ac22148cd9f",
                "srcKUID": "h3ab62bcde764026bd7ee2a8bfab752f",
                "wType": "Label"
            }
        },
        "MobileCustomDropdown.lblTimeperiodContent": {
            "__events__": {},
            "__info__": {
                "kuid": "a99a743721d84c00840fd6e1ccbf6597",
                "srcKUID": "b0f73883e8d4405d81523144dff4c534",
                "wType": "Label"
            }
        },
        "MobileCustomDropdown.lblTypeOfAccounts": {
            "__events__": {},
            "__info__": {
                "kuid": "a847239bb5c34ba884e64e886dd52b8b",
                "srcKUID": "fd199763413e4e498d831ae441f4c893",
                "wType": "Label"
            }
        },
        "MobileCustomDropdown.lblView": {
            "__events__": {},
            "__info__": {
                "kuid": "j3e8d751609a4b3e9c577e3c495b1a32",
                "srcKUID": "jb3e567d2e71428a92a71bc97d0cd883",
                "wType": "Label"
            }
        },
        "MobileCustomDropdown.lblViewType": {
            "__events__": {},
            "__info__": {
                "kuid": "f71a9b019a454b4f99bff4617e8b0d99",
                "srcKUID": "faa6193ed60d4935a80e7bfe1877aa25",
                "wType": "Label"
            }
        },
        "MobileCustomDropdown.segCurrency": {
            "__events__": {},
            "__info__": {
                "kuid": "f1b450a4dbe145f898741f2182a85b6d",
                "srcKUID": "acab853115f34856abc8e9ab01c27219",
                "wType": "Segment"
            }
        },
        "MobileCustomDropdown.segProcessingType": {
            "__events__": {},
            "__info__": {
                "kuid": "ad061a098fd84bd589376d760974df5c",
                "srcKUID": "d00c74e2c97341d0807354bf97efb897",
                "wType": "Segment"
            }
        },
        "MobileCustomDropdown.segTimePeriod": {
            "__events__": {},
            "__info__": {
                "kuid": "d28533c6ca5b4587bb9bb0cf78e6f75a",
                "srcKUID": "edb44217dcad4cdb93ca85adae12b969",
                "wType": "Segment"
            }
        },
        "MobileCustomDropdown.segTypeOfAccounts": {
            "__events__": {},
            "__info__": {
                "kuid": "cc0c69158806417586f260a94d437b90",
                "srcKUID": "d00129c34b254803b93f20417781161f",
                "wType": "Segment"
            }
        },
        "MobileCustomDropdown.segViewTypes": {
            "__events__": {},
            "__info__": {
                "kuid": "b4410f7e18484761aa0d090f01805bb3",
                "srcKUID": "b1dbfab142b74a0888bbd4f308723d35",
                "wType": "Segment"
            }
        },
        "PaginationContainer": {
            "__events__": {},
            "__info__": {
                "kuid": "a2773f04226c4003a1dd2c281363f8c6",
                "srcKUID": "edfe6156f0b84602bb4f46af14fa0161",
                "wType": "UserWidgetInstance"
            }
        },
        "PaginationContainer.flxPagination": {
            "__events__": {},
            "__info__": {
                "kuid": "iba4b70af7644961b30357b0f59769ec",
                "srcKUID": "c663a89e0c834b0f9e979138ce9e055a",
                "wType": "FlexContainer"
            },
            "centerX": {},
            "responsiveData": {
                "b1": {
                    "centerX": {
                        "type": "string",
                        "value": ""
                    },
                    "width": {
                        "type": "string",
                        "value": "40%"
                    }
                },
                "b2": {
                    "width": {
                        "type": "string",
                        "value": "35%"
                    }
                },
                "b3": {
                    "centerX": {
                        "type": "string",
                        "value": "50%"
                    },
                    "isVisible": true,
                    "width": {
                        "type": "string",
                        "value": "60%"
                    }
                },
                "b4": {
                    "width": {
                        "type": "string",
                        "value": "40%"
                    }
                }
            },
            "width": {}
        },
        "PaginationContainer.flxPaginationFirst": {
            "__events__": {},
            "__info__": {
                "kuid": "f891c9037b3143f5bfc2672938259c94",
                "srcKUID": "f08658f862e14ef1898e467fa5349769",
                "wType": "FlexContainer"
            }
        },
        "PaginationContainer.flxPaginationLast": {
            "__events__": {},
            "__info__": {
                "kuid": "cc711a8c008140a0bfdb694a170fdb84",
                "srcKUID": "d689f702bc364e5fbacde2477dfc4601",
                "wType": "FlexContainer"
            }
        },
        "PaginationContainer.flxPaginationNext": {
            "__events__": {},
            "__info__": {
                "kuid": "g80df8c803924a49bda912df9c443bcf",
                "srcKUID": "h53e12a087674c628a337fc4ceed1b31",
                "wType": "FlexContainer"
            }
        },
        "PaginationContainer.flxPaginationPrevious": {
            "__events__": {},
            "__info__": {
                "kuid": "ed44ebf48e5f4c2ebf3d2beb424fcabf",
                "srcKUID": "cd9298134b3d4c9981b8a5070a686fd3",
                "wType": "FlexContainer"
            },
            "autogrowMode": {
                "Default": 0
            },
            "height": {
                "Default": {
                    "type": "string",
                    "value": "40dp"
                }
            },
            "responsiveData": {
                "b3": {}
            },
            "width": {
                "Default": {
                    "type": "string",
                    "value": "40dp"
                }
            }
        },
        "PaginationContainer.imgPaginationFirst": {
            "__events__": {},
            "__info__": {
                "kuid": "f02e71f638a64376a45203a606fd5ba3",
                "srcKUID": "i5233087c0c2473395a35aacc6e537ca",
                "wType": "Image"
            }
        },
        "PaginationContainer.imgPaginationLast": {
            "__events__": {},
            "__info__": {
                "kuid": "df9ce9027a26453ba6747c61fa392cc3",
                "srcKUID": "fb647e548cf0486f83a8ce0d71382409",
                "wType": "Image"
            }
        },
        "PaginationContainer.imgPaginationNext": {
            "__events__": {},
            "__info__": {
                "kuid": "ee1ddc48f251425a8499c06639287fd7",
                "srcKUID": "f5a54a05e8494c958d6c505f853c4688",
                "wType": "Image"
            },
            "src": "pagination_next_active.png"
        },
        "PaginationContainer.imgPaginationPrevious": {
            "__events__": {},
            "__info__": {
                "kuid": "bc3c78f922574f20878bc4be9275f6c7",
                "srcKUID": "e32a9014ca144b3696946eedadb9cbf5",
                "wType": "Image"
            },
            "src": "pagination_back_inactive.png"
        },
        "PaginationContainer.lblPagination": {
            "__events__": {},
            "__info__": {
                "kuid": "d8f4142211c44460a294598cce0fc504",
                "srcKUID": "ef5bf84a49cb4040ab9cc2779d014457",
                "wType": "Label"
            }
        },
        "TabBodyNew": {
            "__events__": {},
            "__info__": {
                "kuid": "daa498a9ba3e430ba9a0665f968753b3",
                "srcKUID": "b07b31bc584944d3a6a6ff591334b6dc",
                "wType": "UserWidgetInstance"
            },
            "minHeight": {
                "Default": {
                    "type": "number",
                    "value": ""
                }
            },
            "responsiveData": {
                "b3": {
                    "minHeight": {
                        "type": "string",
                        "value": "420dp"
                    }
                }
            }
        },
        "TabBodyNew.segTemplates": {
            "__events__": {},
            "__info__": {
                "kuid": "e1bf70892f114147b8e1278d95f59a61",
                "srcKUID": "c6ca5c88f72444d19924de5115a95914",
                "wType": "Segment"
            },
            "left": {
                "Default": {
                    "type": "string",
                    "value": "0dp"
                }
            },
            "responsiveData": {
                "b3": {}
            },
            "top": {
                "Default": {
                    "type": "string",
                    "value": "0dp"
                }
            }
        },
        "TabPaneNew": {
            "__events__": {},
            "__info__": {
                "isRoot": true,
                "kuid": "dfe3dd19ebda48b2a7959bd453a0a053",
                "srcKUID": "g4f0753b9c12467c9de0e2bc6a812f3a",
                "wType": "FlexContainer"
            },
            "bottom": {
                "Default": {
                    "type": "string",
                    "value": ""
                }
            },
            "left": {
                "Default": {
                    "type": "string",
                    "value": ""
                }
            },
            "maxWidth": {
                "Default": {
                    "type": "string",
                    "value": ""
                }
            },
            "responsiveData": {
                "b2": {},
                "b3": {},
                "b4": {
                    "top": {
                        "type": "string",
                        "value": "0dp"
                    }
                }
            },
            "top": {
                "Default": {
                    "type": "string",
                    "value": "0dp"
                }
            },
            "width": {
                "Default": {
                    "type": "ref",
                    "value": "preferred"
                }
            },
            "zIndex": {
                "Default": 1
            }
        },
        "TabSearchBarNew": {
            "__events__": {},
            "__info__": {
                "kuid": "a14a3e0f8c974e548f1c32555df1e702",
                "srcKUID": "dd36902d99844f5cad21c18ddcb3a196",
                "wType": "UserWidgetInstance"
            },
            "autogrowMode": {
                "Default": 0
            },
            "height": {},
            "layoutType": 3,
            "responsiveData": {
                "b1": {
                    "zIndex": 5
                },
                "b2": {
                    "width": {
                        "type": "string",
                        "value": "100%"
                    },
                    "zIndex": 5
                },
                "b3": {
                    "height": {
                        "type": "string",
                        "value": "100dp"
                    },
                    "top": {
                        "type": "string",
                        "value": "0dp"
                    },
                    "width": {
                        "type": "string",
                        "value": "100%"
                    }
                },
                "b4": {
                    "width": {
                        "type": "string",
                        "value": "100%"
                    },
                    "zIndex": 5
                }
            },
            "width": {},
            "zIndex": {
                "Default": 1
            }
        },
        "TabSearchBarNew.MobileCustomDropdown": {
            "__events__": {},
            "__info__": {
                "kuid": "a691d58c13654bafbc30e27fc714fdc3",
                "srcKUID": "h33965cb508e434eb38eb26244d08295",
                "wType": "FlexContainer"
            },
            "autogrowMode": {
                "Default": 0
            },
            "bottom": {
                "Default": {
                    "type": "number",
                    "value": ""
                }
            },
            "height": {
                "Default": {
                    "type": "string",
                    "value": "80dp"
                }
            },
            "isVisible": false,
            "responsiveData": {
                "b1": {
                    "bottom": {
                        "type": "string",
                        "value": ""
                    },
                    "height": {
                        "type": "string",
                        "value": "50dp"
                    },
                    "isVisible": true
                },
                "b2": {
                    "height": {
                        "type": "string",
                        "value": "50dp"
                    },
                    "isVisible": true
                },
                "b4": {
                    "height": {
                        "type": "string",
                        "value": "50dp"
                    },
                    "isVisible": true
                }
            }
        },
        "TabSearchBarNew.MobileCustomDropdown.CopyflxTimePeriodSeparator0iad4443c80964c": {
            "__events__": {},
            "__info__": {
                "kuid": "b2ed19dd5bf14dd1a512c7402cd2830e",
                "srcKUID": "fed9f4152f2c4c9fb0a88b4dc67fb6f5",
                "wType": "FlexContainer"
            }
        },
        "TabSearchBarNew.MobileCustomDropdown.btnApplyFilter": {
            "__events__": {},
            "__info__": {
                "kuid": "d0e2dce8a99747a9a0ec119bf47946ec",
                "srcKUID": "d24a1ada27b44e14ab7b865e5fcd15ca",
                "wType": "Button"
            }
        },
        "TabSearchBarNew.MobileCustomDropdown.btnCancelFilter": {
            "__events__": {},
            "__info__": {
                "kuid": "d7d9ce567b094632898e84e311dcff26",
                "srcKUID": "h0faed312e8f4660b0b4e5fb1331e9bc",
                "wType": "Button"
            }
        },
        "TabSearchBarNew.MobileCustomDropdown.flxAll": {
            "__events__": {},
            "__info__": {
                "kuid": "fb0e4b36612e4602990c08f2bb0d4bdb",
                "srcKUID": "acf75c5c6bb54e819dcb82aa765148d4",
                "wType": "FlexContainer"
            }
        },
        "TabSearchBarNew.MobileCustomDropdown.flxApprovalTypeSeparator": {
            "__events__": {},
            "__info__": {
                "kuid": "bb53d3341f314f46a87a2805d75dd840",
                "srcKUID": "h843acdee54e4eccbf570a95c2f11edd",
                "wType": "FlexContainer"
            }
        },
        "TabSearchBarNew.MobileCustomDropdown.flxApproveType": {
            "__events__": {},
            "__info__": {
                "kuid": "a3558306c2324a8e938c8097284a1f1b",
                "srcKUID": "ed7920969dcf4fc5b58100bf404504f2",
                "wType": "FlexContainer"
            }
        },
        "TabSearchBarNew.MobileCustomDropdown.flxButtons": {
            "__events__": {},
            "__info__": {
                "kuid": "g9a4fab9c49147aeb8a3760b2578c8f1",
                "srcKUID": "d684e2f2ee0f4f0da443b31b2ea24d90",
                "wType": "FlexContainer"
            }
        },
        "TabSearchBarNew.MobileCustomDropdown.flxCurrencyBody": {
            "__events__": {},
            "__info__": {
                "kuid": "e4c35acdf4874492a725e97933813b68",
                "srcKUID": "h45e1fb86f574ee690a0e4cfd3bd13ec",
                "wType": "FlexContainer"
            }
        },
        "TabSearchBarNew.MobileCustomDropdown.flxCurrencyExpand": {
            "__events__": {},
            "__info__": {
                "kuid": "bde9639ccd5946f78128594508ea6880",
                "srcKUID": "bef7ee59084b45f39adfe897be7c47a3",
                "wType": "FlexContainer"
            }
        },
        "TabSearchBarNew.MobileCustomDropdown.flxCurrencyHeader": {
            "__events__": {},
            "__info__": {
                "kuid": "a36192f2c1b34afb9d9dd090cc3f7516",
                "srcKUID": "c24773708548491f9887868f6a79484d",
                "wType": "FlexContainer"
            }
        },
        "TabSearchBarNew.MobileCustomDropdown.flxCurrencyTitle": {
            "__events__": {},
            "__info__": {
                "kuid": "ba7c98a123884d03914a38eb23b919de",
                "srcKUID": "cc1c84dc55c44409a298957ee1eab086",
                "wType": "FlexContainer"
            }
        },
        "TabSearchBarNew.MobileCustomDropdown.flxDropdown": {
            "__events__": {},
            "__info__": {
                "kuid": "c5e55996f2b24319bec42c49dde85993",
                "srcKUID": "d044f3948dc34ba1b6538e70f48b6aef",
                "wType": "FlexContainer"
            },
            "isVisible": false,
            "left": {
                "Default": {
                    "type": "string",
                    "value": "4%"
                }
            },
            "minWidth": {
                "Default": {
                    "type": "number",
                    "value": ""
                }
            },
            "responsiveData": {
                "b1": {
                    "isVisible": false,
                    "left": {
                        "type": "string",
                        "value": "0%"
                    },
                    "minWidth": {
                        "type": "string",
                        "value": ""
                    },
                    "top": {
                        "type": "string",
                        "value": "100%"
                    },
                    "width": {
                        "type": "string",
                        "value": "100%"
                    }
                },
                "b2": {
                    "isVisible": false,
                    "left": {
                        "type": "string",
                        "value": "0%"
                    },
                    "minWidth": {
                        "type": "string",
                        "value": ""
                    },
                    "top": {
                        "type": "string",
                        "value": "100%"
                    },
                    "width": {
                        "type": "string",
                        "value": "100%"
                    }
                },
                "b4": {
                    "isVisible": false,
                    "left": {
                        "type": "string",
                        "value": "0%"
                    },
                    "top": {
                        "type": "string",
                        "value": "100%"
                    },
                    "width": {
                        "type": "string",
                        "value": "100%"
                    }
                }
            },
            "top": {
                "Default": {
                    "type": "string",
                    "value": "60dp"
                }
            },
            "width": {
                "Default": {
                    "type": "string",
                    "value": "92%"
                }
            }
        },
        "TabSearchBarNew.MobileCustomDropdown.flxDropdownCurrency": {
            "__events__": {},
            "__info__": {
                "kuid": "c7111d55917a49be9fe0d07aee0bd550",
                "srcKUID": "a5bb072f60e84d2bb64878b30b5bcb86",
                "wType": "FlexContainer"
            }
        },
        "TabSearchBarNew.MobileCustomDropdown.flxDropdownImage": {
            "__events__": {},
            "__info__": {
                "kuid": "ac73b3afcc2e4948a873550299091c7c",
                "srcKUID": "e4d891acf4b542db8d0cacb7c9011c11",
                "wType": "FlexContainer"
            }
        },
        "TabSearchBarNew.MobileCustomDropdown.flxFilter": {
            "__events__": {},
            "__info__": {
                "kuid": "b31844fbf2394514b6face26fef0e60b",
                "srcKUID": "d3461492d2ef48f599739b50ceb2b7fe",
                "wType": "FlexContainer"
            }
        },
        "TabSearchBarNew.MobileCustomDropdown.flxImage": {
            "__events__": {},
            "__info__": {
                "kuid": "i95d6178235c4fdf9a0c4fba7e5a8d34",
                "srcKUID": "b41180006e224c45b1edb79f9c721a4c",
                "wType": "FlexContainer"
            }
        },
        "TabSearchBarNew.MobileCustomDropdown.flxIphoneDropdown": {
            "__events__": {},
            "__info__": {
                "kuid": "j4b2a2174fb24ce9a56e8c8558951d9d",
                "srcKUID": "a837e3c73dc74215acd3d38433ef414b",
                "wType": "FlexContainer"
            },
            "autogrowMode": {
                "Default": 0
            },
            "height": {
                "Default": {
                    "type": "string",
                    "value": "40dp"
                }
            },
            "left": {
                "Default": {
                    "type": "string",
                    "value": "4%"
                }
            },
            "minWidth": {
                "Default": {
                    "type": "number",
                    "value": ""
                }
            },
            "responsiveData": {
                "b1": {
                    "height": {
                        "type": "string",
                        "value": "50dp"
                    },
                    "left": {
                        "type": "string",
                        "value": "0%"
                    },
                    "minWidth": {
                        "type": "string",
                        "value": ""
                    },
                    "top": {
                        "type": "string",
                        "value": "0dp"
                    },
                    "width": {
                        "type": "string",
                        "value": "100%"
                    }
                },
                "b2": {
                    "height": {
                        "type": "string",
                        "value": "50dp"
                    },
                    "left": {
                        "type": "string",
                        "value": "0%"
                    },
                    "minWidth": {
                        "type": "string",
                        "value": ""
                    },
                    "top": {
                        "type": "string",
                        "value": "0dp"
                    },
                    "width": {
                        "type": "string",
                        "value": "100%"
                    }
                },
                "b4": {
                    "height": {
                        "type": "string",
                        "value": "50dp"
                    },
                    "left": {
                        "type": "string",
                        "value": "0%"
                    },
                    "minWidth": {
                        "type": "string",
                        "value": ""
                    },
                    "top": {
                        "type": "string",
                        "value": "0dp"
                    },
                    "width": {
                        "type": "string",
                        "value": "100%"
                    }
                }
            },
            "top": {
                "Default": {
                    "type": "string",
                    "value": "20dp"
                }
            },
            "width": {
                "Default": {
                    "type": "string",
                    "value": "92%"
                }
            }
        },
        "TabSearchBarNew.MobileCustomDropdown.flxProcessingType": {
            "__events__": {},
            "__info__": {
                "kuid": "e8e8c7059fab4a90a75168eda06751c3",
                "srcKUID": "e688a7f81051405da7debe919ff730a8",
                "wType": "FlexContainer"
            }
        },
        "TabSearchBarNew.MobileCustomDropdown.flxProcessingTypeBottomSeparator": {
            "__events__": {},
            "__info__": {
                "kuid": "de42022bed3c4834b5fb5e4204a61bd5",
                "srcKUID": "f95212389d924c25bbca2e7bf00ffcc6",
                "wType": "FlexContainer"
            }
        },
        "TabSearchBarNew.MobileCustomDropdown.flxProcessingTypeDropdownImage": {
            "__events__": {},
            "__info__": {
                "kuid": "e2cfe1f6eb4448a4a1310f063a0348cd",
                "srcKUID": "d7223ce04adb4be7b47fd5d346a03a93",
                "wType": "FlexContainer"
            }
        },
        "TabSearchBarNew.MobileCustomDropdown.flxProcessingTypeHeaderContent": {
            "__events__": {},
            "__info__": {
                "kuid": "e0c14b320d974afa85d97e57b2384d13",
                "srcKUID": "d5d5c06aca1245d795ca6e383f8de35c",
                "wType": "FlexContainer"
            }
        },
        "TabSearchBarNew.MobileCustomDropdown.flxProcessingTypeHeaderDropdown": {
            "__events__": {},
            "__info__": {
                "kuid": "ga6d957ef9134e24a8628e6cdcc0a809",
                "srcKUID": "je33c95072ce4f67bfb711ee4cd9d1bd",
                "wType": "FlexContainer"
            }
        },
        "TabSearchBarNew.MobileCustomDropdown.flxProcessingTypeTopSeparator": {
            "__events__": {},
            "__info__": {
                "kuid": "g417bde8e24d44e4877c91c8ab805045",
                "srcKUID": "dfdb1f3509064f4d8a82bbc00f6995af",
                "wType": "FlexContainer"
            }
        },
        "TabSearchBarNew.MobileCustomDropdown.flxSeperatorCurrency": {
            "__events__": {},
            "__info__": {
                "kuid": "g3935085841948599559bc7bd2243a99",
                "srcKUID": "h27f8795e6484efc92367a8ec749d414",
                "wType": "FlexContainer"
            }
        },
        "TabSearchBarNew.MobileCustomDropdown.flxSeperatorToa": {
            "__events__": {},
            "__info__": {
                "kuid": "c9ff257080414a8494692f45ac314e71",
                "srcKUID": "c428d5d580364d8195e659442f79cb54",
                "wType": "FlexContainer"
            }
        },
        "TabSearchBarNew.MobileCustomDropdown.flxSeperatorToaTitle": {
            "__events__": {},
            "__info__": {
                "kuid": "d62a3145ec7e4e0cbee328a79f7ace0c",
                "srcKUID": "ec4c2ddb0b524db09d6b8c140ffaac89",
                "wType": "FlexContainer"
            }
        },
        "TabSearchBarNew.MobileCustomDropdown.flxStatus": {
            "__events__": {},
            "__info__": {
                "kuid": "df1c87e4d3a74e61a0562242b0dcde5b",
                "srcKUID": "b57c71d18434457d9ba1f6c49121e28c",
                "wType": "FlexContainer"
            }
        },
        "TabSearchBarNew.MobileCustomDropdown.flxTimePeriod": {
            "__events__": {},
            "__info__": {
                "kuid": "e3b9d0dd18b04704bf9f6f2d888b805c",
                "srcKUID": "g1df5c90b23847109661b6cd9a2a9285",
                "wType": "FlexContainer"
            }
        },
        "TabSearchBarNew.MobileCustomDropdown.flxTimePeriodDropdownImage": {
            "__events__": {},
            "__info__": {
                "kuid": "d48461b86e914bc9be2f9ebff0311b03",
                "srcKUID": "g8e168eaeac844a680590d3b8dbb7ba3",
                "wType": "FlexContainer"
            }
        },
        "TabSearchBarNew.MobileCustomDropdown.flxTimePeriodHeader": {
            "__events__": {},
            "__info__": {
                "kuid": "cfebbf93ab574939bc04872c3938bf5b",
                "srcKUID": "e7823ca83aa542ff8b47834155f28574",
                "wType": "FlexContainer"
            }
        },
        "TabSearchBarNew.MobileCustomDropdown.flxTimePeriodHeaderDropdown": {
            "__events__": {},
            "__info__": {
                "kuid": "d0d1e6d08e8d41d5a24aec538e8f4eec",
                "srcKUID": "fc071f202a264c76b2d2b2a2e3a8cb61",
                "wType": "FlexContainer"
            }
        },
        "TabSearchBarNew.MobileCustomDropdown.flxTimePeriodSeparator": {
            "__events__": {},
            "__info__": {
                "kuid": "ce42b5711b2e47e899df047e0d44b1f9",
                "srcKUID": "d54c5265bac440f9a201bfbcaad0e6cb",
                "wType": "FlexContainer"
            }
        },
        "TabSearchBarNew.MobileCustomDropdown.flxTimeperiodBody": {
            "__events__": {},
            "__info__": {
                "kuid": "fbc502ce66d44a64ab142013b669a3c3",
                "srcKUID": "f489c61629df4302a018420c35f62590",
                "wType": "FlexContainer"
            }
        },
        "TabSearchBarNew.MobileCustomDropdown.flxTimeperiodHeaderContent": {
            "__events__": {},
            "__info__": {
                "kuid": "f79e6a150d0e4c959efbe16ddd456bed",
                "srcKUID": "d3b90e156a4e490a90aaed0ce957c109",
                "wType": "FlexContainer"
            }
        },
        "TabSearchBarNew.MobileCustomDropdown.flxToaBody": {
            "__events__": {},
            "__info__": {
                "kuid": "b63237f29b214770baffe767f3f831ed",
                "srcKUID": "a857644e801b4118aaa14029f669b86c",
                "wType": "FlexContainer"
            }
        },
        "TabSearchBarNew.MobileCustomDropdown.flxToaHeader": {
            "__events__": {},
            "__info__": {
                "kuid": "ff6a467f481349d5a8f788035d96e268",
                "srcKUID": "fbfdc92fbc964946bdbac10b32eb8f8f",
                "wType": "FlexContainer"
            }
        },
        "TabSearchBarNew.MobileCustomDropdown.flxToaHeaderTitle": {
            "__events__": {},
            "__info__": {
                "kuid": "e9b8d6923c354c2f91bb4f2de8dfe1b2",
                "srcKUID": "dc0c8319b5754dcdb7bae69465913fff",
                "wType": "FlexContainer"
            }
        },
        "TabSearchBarNew.MobileCustomDropdown.flxTypeOfAccountsExpand": {
            "__events__": {},
            "__info__": {
                "kuid": "dbe6370741fc466cbb35737a7ded4352",
                "srcKUID": "f4f5399119cc4ca5ab28fc6d10e1a8a5",
                "wType": "FlexContainer"
            }
        },
        "TabSearchBarNew.MobileCustomDropdown.flxprocessingTypeBody": {
            "__events__": {},
            "__info__": {
                "kuid": "gee487f4df2a40d2ad50ddc7a1a75d76",
                "srcKUID": "e08c72f404f043618e32b560f0d9e043",
                "wType": "FlexContainer"
            }
        },
        "TabSearchBarNew.MobileCustomDropdown.flxprocessingTypeHeader": {
            "__events__": {},
            "__info__": {
                "kuid": "a7db9c78c58942629e9121c572653a85",
                "srcKUID": "j38b19242ba249159bbb4aa4d55209a4",
                "wType": "FlexContainer"
            }
        },
        "TabSearchBarNew.MobileCustomDropdown.imgDropdown": {
            "__events__": {},
            "__info__": {
                "kuid": "c04a634ecee74c379709740cea72d763",
                "srcKUID": "f45c93006be54d7caa1efc377ddfe3e8",
                "wType": "Image"
            },
            "src": "listboxarw.png"
        },
        "TabSearchBarNew.MobileCustomDropdown.imgDropdownTimeperiod": {
            "__events__": {},
            "__info__": {
                "kuid": "f75c7875b6f44b6a9d93e034d0614cc6",
                "srcKUID": "g0c345cb318f487cade60b5e9faa1144",
                "wType": "Label"
            }
        },
        "TabSearchBarNew.MobileCustomDropdown.imgDropdownprocessingType": {
            "__events__": {},
            "__info__": {
                "kuid": "eced206ce2434f4aabcfb12316857973",
                "srcKUID": "f463c0d97ddc4084be506f904b806ca9",
                "wType": "Label"
            }
        },
        "TabSearchBarNew.MobileCustomDropdown.lblAll": {
            "__events__": {},
            "__info__": {
                "kuid": "f5c673b6a2b945558edf0fc98733d422",
                "srcKUID": "ca19dcf966864a3dad7d63ad4b2b81f2",
                "wType": "Label"
            }
        },
        "TabSearchBarNew.MobileCustomDropdown.lblAllValue": {
            "__events__": {},
            "__info__": {
                "kuid": "j3833fcf453f4376a0aba0300c19154f",
                "srcKUID": "dafa67f911044945aaac4167190aa8f3",
                "wType": "Label"
            }
        },
        "TabSearchBarNew.MobileCustomDropdown.lblCurrencyType": {
            "__events__": {},
            "__info__": {
                "kuid": "aa5baa9d5ee743469c01affb7aadd656",
                "srcKUID": "df71f39211c24ff6840c6304338ae3d8",
                "wType": "Label"
            }
        },
        "TabSearchBarNew.MobileCustomDropdown.lblFilterCount": {
            "__events__": {},
            "__info__": {
                "kuid": "cbd9aed7226349baa80db50c292c49f1",
                "srcKUID": "i05d39687c4648448caffa493b955b16",
                "wType": "Label"
            }
        },
        "TabSearchBarNew.MobileCustomDropdown.lblImage": {
            "__events__": {},
            "__info__": {
                "kuid": "a47f4cc4b25b42cbb7e7388674e3c500",
                "srcKUID": "adc0f2c58c984189a52d245e8375ded2",
                "wType": "Label"
            }
        },
        "TabSearchBarNew.MobileCustomDropdown.lblImageCurrency": {
            "__events__": {},
            "__info__": {
                "kuid": "b75810276a8d4ee8aa05220defe65ebd",
                "srcKUID": "j74e7ac41f1a42039607d237c8b01c59",
                "wType": "Label"
            }
        },
        "TabSearchBarNew.MobileCustomDropdown.lblProcessingTypeContent": {
            "__events__": {},
            "__info__": {
                "kuid": "j58f0a75c40747fdbe9271cc6974447f",
                "srcKUID": "ca265660332149538212a083069cb41c",
                "wType": "Label"
            }
        },
        "TabSearchBarNew.MobileCustomDropdown.lblTimeperiodContent": {
            "__events__": {},
            "__info__": {
                "kuid": "b3286c69c8f445f88593b8cb4c40f72e",
                "srcKUID": "gd9c401602994ca4aac99d44df1e751c",
                "wType": "Label"
            }
        },
        "TabSearchBarNew.MobileCustomDropdown.lblTypeOfAccounts": {
            "__events__": {},
            "__info__": {
                "kuid": "b78fec40ca5f4016894e72302a56e325",
                "srcKUID": "c13462d105604a2c97f4563a9488ab3e",
                "wType": "Label"
            }
        },
        "TabSearchBarNew.MobileCustomDropdown.lblView": {
            "__events__": {},
            "__info__": {
                "kuid": "dd18e574e6244c5597838f3bb5476185",
                "srcKUID": "b3b82733506f439996120a336758532b",
                "wType": "Label"
            },
            "left": {
                "Default": {
                    "type": "string",
                    "value": "1%"
                }
            },
            "minWidth": {
                "Default": {
                    "type": "number",
                    "value": ""
                }
            },
            "responsiveData": {
                "b1": {
                    "left": {
                        "type": "string",
                        "value": ""
                    },
                    "minWidth": {
                        "type": "string",
                        "value": ""
                    },
                    "right": {
                        "type": "string",
                        "value": "72%"
                    },
                    "width": {
                        "type": "string",
                        "value": "20%"
                    }
                },
                "b2": {
                    "left": {
                        "type": "string",
                        "value": ""
                    },
                    "minWidth": {
                        "type": "string",
                        "value": ""
                    },
                    "right": {
                        "type": "string",
                        "value": "72%"
                    },
                    "width": {
                        "type": "string",
                        "value": "20%"
                    }
                },
                "b4": {
                    "left": {
                        "type": "string",
                        "value": ""
                    },
                    "minWidth": {
                        "type": "string",
                        "value": ""
                    },
                    "right": {
                        "type": "string",
                        "value": "72%"
                    },
                    "width": {
                        "type": "string",
                        "value": "20%"
                    }
                }
            },
            "right": {
                "Default": {
                    "type": "number",
                    "value": ""
                }
            },
            "width": {
                "Default": {
                    "type": "string",
                    "value": "4%"
                }
            }
        },
        "TabSearchBarNew.MobileCustomDropdown.lblViewType": {
            "__events__": {},
            "__info__": {
                "kuid": "a1de39a7be254ba7aadc73214fac355f",
                "srcKUID": "j14d651ae4dd4829b6c796b4a29a7ea9",
                "wType": "Label"
            },
            "left": {
                "Default": {
                    "type": "string",
                    "value": "5%"
                }
            },
            "minWidth": {
                "Default": {
                    "type": "number",
                    "value": ""
                }
            },
            "responsiveData": {
                "b1": {
                    "left": {
                        "type": "string",
                        "value": ""
                    },
                    "minWidth": {
                        "type": "string",
                        "value": ""
                    },
                    "right": {
                        "type": "string",
                        "value": "12%"
                    },
                    "text": "All",
                    "width": {
                        "type": "string",
                        "value": "60%"
                    }
                },
                "b2": {
                    "left": {
                        "type": "string",
                        "value": ""
                    },
                    "minWidth": {
                        "type": "string",
                        "value": ""
                    },
                    "right": {
                        "type": "string",
                        "value": "12%"
                    },
                    "text": "All",
                    "width": {
                        "type": "string",
                        "value": "60%"
                    }
                },
                "b4": {
                    "left": {
                        "type": "string",
                        "value": ""
                    },
                    "minWidth": {
                        "type": "string",
                        "value": ""
                    },
                    "right": {
                        "type": "string",
                        "value": "12%"
                    },
                    "text": "All",
                    "width": {
                        "type": "string",
                        "value": "60%"
                    }
                }
            },
            "right": {
                "Default": {
                    "type": "number",
                    "value": ""
                }
            },
            "text": "All Transactions",
            "width": {
                "Default": {
                    "type": "string",
                    "value": "85%"
                }
            }
        },
        "TabSearchBarNew.MobileCustomDropdown.segCurrency": {
            "__events__": {},
            "__info__": {
                "kuid": "e9937302fe8c41449adc078823ec2ae8",
                "srcKUID": "a8ca02b908d2452bb89f87681663f63e",
                "wType": "Segment"
            }
        },
        "TabSearchBarNew.MobileCustomDropdown.segProcessingType": {
            "__events__": {},
            "__info__": {
                "kuid": "f42f5e7712fa48d78474e63323e1976c",
                "srcKUID": "b5d042f0ac9a4a5a97aa4f90055f8390",
                "wType": "Segment"
            }
        },
        "TabSearchBarNew.MobileCustomDropdown.segTimePeriod": {
            "__events__": {},
            "__info__": {
                "kuid": "cd42effae29c40e39e72f6aab547dcc6",
                "srcKUID": "jfffab6fde3a4803a0af65e9494af34e",
                "wType": "Segment"
            }
        },
        "TabSearchBarNew.MobileCustomDropdown.segTypeOfAccounts": {
            "__events__": {},
            "__info__": {
                "kuid": "e8b92fecea8e42a597c35fc9ea579165",
                "srcKUID": "aa40a6c9eccd4f71a7f76f659cee756d",
                "wType": "Segment"
            }
        },
        "TabSearchBarNew.MobileCustomDropdown.segViewTypes": {
            "__events__": {},
            "__info__": {
                "kuid": "b1e6f44a70cb4ab09df61637a8712386",
                "srcKUID": "a7369429bf8e4fda8276159c733f9f57",
                "wType": "Segment"
            }
        },
        "TabSearchBarNew.RadioButtonGroup0e9b89fa4f5e74c": {
            "__events__": {},
            "__info__": {
                "kuid": "dd53c45014c74197a6580c0376abbc26",
                "srcKUID": "b3b908c488fc4f04974ee28c034734d0",
                "wType": "RadioButtonGroup"
            }
        },
        "TabSearchBarNew.btnAdvancedSearch": {
            "__events__": {},
            "__info__": {
                "kuid": "ca6bfc2bb6d845daa1423d3c4ad0ed71",
                "srcKUID": "f56dc121b5cd4aa98c0a77a2c01ea22e",
                "wType": "Button"
            }
        },
        "TabSearchBarNew.flxBoxSearch": {
            "__events__": {},
            "__info__": {
                "kuid": "c9a8c4bd760444c6a76863114c1f80e7",
                "srcKUID": "a0d24cfb1bc3492aba795e313ff89324",
                "wType": "FlexContainer"
            },
            "autogrowMode": {
                "Default": 0
            },
            "centerY": {},
            "height": {
                "Default": {
                    "type": "string",
                    "value": "40dp"
                }
            },
            "left": {},
            "responsiveData": {
                "b1": {
                    "height": {
                        "type": "string",
                        "value": "50dp"
                    }
                },
                "b2": {
                    "height": {
                        "type": "string",
                        "value": "50dp"
                    }
                },
                "b3": {
                    "centerY": {
                        "type": "string",
                        "value": "50%"
                    },
                    "left": {
                        "type": "string",
                        "value": "0%"
                    },
                    "width": {
                        "type": "string",
                        "value": "100%"
                    }
                },
                "b4": {
                    "height": {
                        "type": "string",
                        "value": "50dp"
                    }
                }
            },
            "width": {
                "Default": {
                    "type": "string",
                    "value": "97%"
                }
            }
        },
        "TabSearchBarNew.flxDropDown": {
            "__events__": {},
            "__info__": {
                "kuid": "c1be53a00b184912a82864a7bf9be57b",
                "srcKUID": "gbda7ae8fdc84d63baa77e32d26a8a90",
                "wType": "FlexContainer"
            },
            "autogrowMode": {
                "Default": 0
            },
            "centerY": {},
            "height": {},
            "left": {
                "Default": {
                    "type": "string",
                    "value": "0%"
                }
            },
            "responsiveData": {
                "b1": {
                    "height": {
                        "type": "string",
                        "value": "50dp"
                    },
                    "width": null
                },
                "b2": {
                    "width": null
                },
                "b3": {
                    "centerY": {
                        "type": "string",
                        "value": "30%"
                    },
                    "height": {
                        "type": "string",
                        "value": "40dp"
                    },
                    "isVisible": false,
                    "width": null
                },
                "b4": {
                    "height": {
                        "type": "string",
                        "value": "50dp"
                    },
                    "width": null
                }
            },
            "width": {
                "Default": {
                    "type": "string",
                    "value": "28%"
                }
            }
        },
        "TabSearchBarNew.flxOptions": {
            "__events__": {},
            "__info__": {
                "kuid": "e8b0e4d6f60d4402bca6aa61f4be03ee",
                "srcKUID": "dec94ee33eef41408156741a0c4c8de9",
                "wType": "FlexContainer"
            }
        },
        "TabSearchBarNew.flxSearch": {
            "__events__": {},
            "__info__": {
                "kuid": "fb9c3339eaa1499dae13920367d50bc2",
                "srcKUID": "e1c5851255be402fbcc59c45d3c6c465",
                "wType": "FlexContainer"
            },
            "autogrowMode": {
                "Default": 0
            },
            "centerY": {},
            "height": {},
            "left": {
                "Default": {
                    "type": "string",
                    "value": "20dp"
                }
            },
            "responsiveData": {
                "b3": {
                    "centerY": {
                        "type": "string",
                        "value": "50%"
                    },
                    "height": {
                        "type": "string",
                        "value": "40dp"
                    },
                    "left": {
                        "type": "string",
                        "value": "3.75%"
                    },
                    "top": {
                        "type": "string",
                        "value": "0dp"
                    },
                    "width": {
                        "type": "string",
                        "value": "95.75%"
                    }
                }
            },
            "top": {},
            "width": {
                "Default": {
                    "type": "string",
                    "value": "66%"
                }
            }
        },
        "TabSearchBarNew.flxToggleOptions": {
            "__events__": {},
            "__info__": {
                "kuid": "ga0dd6a76b5241609c8a02dbd20ecc5c",
                "srcKUID": "a00a581f094b47f5bef5fb1999466919",
                "wType": "FlexContainer"
            }
        },
        "TabSearchBarNew.imgClear": {
            "__events__": {},
            "__info__": {
                "kuid": "daf84db02dfb4a11bc9128b1bd4d540f",
                "srcKUID": "da02efee27904520abb85f764d3982c4",
                "wType": "Label"
            }
        },
        "TabSearchBarNew.imgOption0": {
            "__events__": {},
            "__info__": {
                "kuid": "ff003576130844b4801a8a08bb27aaba",
                "srcKUID": "aa1c52011dac49ec8ed0e3fa0a3ed328",
                "wType": "Label"
            }
        },
        "TabSearchBarNew.imgOption1": {
            "__events__": {},
            "__info__": {
                "kuid": "f7e3ce935cb1434a99b41cec981c4414",
                "srcKUID": "c8cc07c404b447beb2a57ff249a6167c",
                "wType": "Label"
            }
        },
        "TabSearchBarNew.imgSearch": {
            "__events__": {},
            "__info__": {
                "kuid": "dd47fb87bca3482eb4ea57a00adacb76",
                "srcKUID": "d5fd1fe8348949acab88ebffbbaa0b1c",
                "wType": "Label"
            },
            "bottom": {
                "Default": {
                    "type": "number",
                    "value": ""
                }
            },
            "centerY": {},
            "left": {},
            "responsiveData": {
                "b3": {
                    "centerY": {
                        "type": "string",
                        "value": "55%"
                    },
                    "height": {
                        "type": "string",
                        "value": "70%"
                    },
                    "left": {
                        "type": "string",
                        "value": "11dp"
                    }
                }
            },
            "top": {
                "Default": {
                    "type": "string",
                    "value": "0"
                }
            }
        },
        "TabSearchBarNew.lblOption0": {
            "__events__": {},
            "__info__": {
                "kuid": "fa88d74aed014acda030e178d6da5fff",
                "srcKUID": "h69101d857c7479ea95bdede1de9b3f4",
                "wType": "Label"
            }
        },
        "TabSearchBarNew.lblOption1": {
            "__events__": {},
            "__info__": {
                "kuid": "be9e5b149be74feda170ccf72980922b",
                "srcKUID": "a69c7f305efe43649f5045b6926ac266",
                "wType": "Label"
            }
        },
        "TabSearchBarNew.lblView": {
            "__events__": {},
            "__info__": {
                "kuid": "a3891922e3b44c718d70b9ab2bb89fc1",
                "srcKUID": "h270f000ceb9409599d6d2fcb2d2b977",
                "wType": "Label"
            },
            "isVisible": true,
            "responsiveData": {
                "b1": {
                    "isVisible": false
                },
                "b2": {
                    "isVisible": false
                },
                "b4": {
                    "isVisible": false
                }
            }
        },
        "TabSearchBarNew.listBoxViewType": {
            "__events__": {},
            "__info__": {
                "kuid": "ff9d26a1e98b43108d9ffbe4b5241d38",
                "srcKUID": "ad0738b413b349a880f2e292b3da4f59",
                "wType": "ListBox"
            },
            "isVisible": true,
            "responsiveData": {
                "b1": {
                    "isVisible": false
                },
                "b2": {
                    "isVisible": false
                },
                "b4": {
                    "isVisible": false
                }
            },
            "right": {
                "Default": {
                    "type": "string",
                    "value": "2dp"
                }
            },
            "width": {
                "Default": {
                    "type": "string",
                    "value": "71%"
                }
            }
        },
        "TabSearchBarNew.tbxSearch": {
            "__events__": {},
            "__info__": {
                "kuid": "b03e447865e849ccb8f2b43891e0c9b0",
                "srcKUID": "d25554bd28f64aeead79a236a1a7e909",
                "wType": "TextField"
            },
            "i18n_text": "i18n.myapprovals.SearchTransactionOrTemplate",
            "left": {
                "Default": {
                    "type": "string",
                    "value": "45dp"
                }
            },
            "responsiveData": {
                "b3": {
                    "centerY": {
                        "type": "string",
                        "value": "50%"
                    },
                    "left": {
                        "type": "string",
                        "value": "37dp"
                    },
                    "width": {
                        "type": "string",
                        "value": "88%"
                    }
                }
            },
            "width": {}
        },
        "TabsHeaderNew": {
            "__events__": {},
            "__info__": {
                "kuid": "e223f8a625dc472493f5e5302ba17167",
                "srcKUID": "b9fafb9e11d542f0818b94573c6d84c9",
                "wType": "UserWidgetInstance"
            },
            "clipBounds": false,
            "responsiveData": {
                "b3": {
                    "zIndex": 10
                },
                "b4": {
                    "width": {
                        "type": "string",
                        "value": "100%"
                    }
                }
            },
            "width": {}
        },
        "TabsHeaderNew.btnTab1": {
            "__events__": {},
            "__info__": {
                "kuid": "b2df4aca1d8a4ee29274d19fdc59dac8",
                "srcKUID": "jba8dd9442634e26890db8dd9f2e9f0f",
                "wType": "Button"
            },
            "i18n_text": "i18n.kony.BulkPayments.bulkPaymentHeader",
            "isVisible": false,
            "left": {
                "Default": {
                    "type": "string",
                    "value": "2.64%"
                }
            },
            "responsiveData": {
                "b1": {
                    "isVisible": null
                },
                "b3": {
                    "left": {
                        "type": "string",
                        "value": "3.75%"
                    },
                    "width": {
                        "type": "string",
                        "value": "45%"
                    }
                }
            },
            "width": {
                "Default": {
                    "type": "string",
                    "value": "21%"
                }
            }
        },
        "TabsHeaderNew.btnTab2": {
            "__events__": {},
            "__info__": {
                "kuid": "d39d6cb0b4f24a7da922c27b961cca68",
                "srcKUID": "f395c01f4aa44996b55cda064c966080",
                "wType": "Button"
            },
            "i18n_text": "i18n.konybb.Common.ACHTransactions",
            "isVisible": true,
            "left": {
                "Default": {
                    "type": "string",
                    "value": "3.51%"
                }
            },
            "responsiveData": {
                "b1": {
                    "isVisible": false
                },
                "b3": {
                    "left": {
                        "type": "string",
                        "value": "3.75%"
                    },
                    "width": {
                        "type": "string",
                        "value": "46.70%"
                    }
                }
            },
            "width": {}
        },
        "TabsHeaderNew.btnTab3": {
            "__events__": {},
            "__info__": {
                "kuid": "i996734bfbf74d05899544159fd43158",
                "srcKUID": "jc5c064251484a64b85abc1166dc20aa",
                "wType": "Button"
            },
            "isVisible": true,
            "responsiveData": {
                "b1": {
                    "isVisible": false
                },
                "b3": {
                    "width": {
                        "type": "string",
                        "value": "25%"
                    }
                }
            },
            "width": {}
        },
        "TabsHeaderNew.btnTab4": {
            "__events__": {},
            "__info__": {
                "kuid": "j2a55020a1e54e75b01b902191f9fcf2",
                "srcKUID": "id0e330425f64cbd91cfe9f9a372eef7",
                "wType": "Button"
            },
            "isVisible": false,
            "responsiveData": {}
        },
        "TabsHeaderNew.btnTab5": {
            "__events__": {},
            "__info__": {
                "kuid": "f0b3f44b441a4d3bb85a4cdf3cb7a04e",
                "srcKUID": "d73b44134968426f925568f6699a2d90",
                "wType": "Button"
            },
            "isVisible": false,
            "responsiveData": {}
        },
        "TabsHeaderNew.btnTab6": {
            "__events__": {},
            "__info__": {
                "kuid": "ea6cdb00d61341bf8a49c446bbee51a9",
                "srcKUID": "c49baf28eda841b9ae9f697bd154ed87",
                "wType": "Button"
            },
            "isVisible": false,
            "responsiveData": {}
        },
        "flxContentContainer": {
            "__events__": {},
            "__info__": {
                "kuid": "bf0392750b344141808b1ab48ea74d99",
                "srcKUID": "ecb73014692245bbac56508a6da45260",
                "wType": "FlexContainer"
            },
            "bottom": {},
            "left": {},
            "minHeight": {
                "Default": {
                    "type": "number",
                    "value": ""
                }
            },
            "responsiveData": {
                "b3": {
                    "bottom": {
                        "type": "string",
                        "value": ""
                    },
                    "left": {
                        "type": "string",
                        "value": "0dp"
                    },
                    "minHeight": {
                        "type": "string",
                        "value": ""
                    },
                    "top": {
                        "type": "string",
                        "value": "0dp"
                    },
                    "width": {
                        "type": "string",
                        "value": "100%"
                    }
                }
            },
            "top": {},
            "width": {}
        }
    },
    "enablescrolling": true,
    "id": "TabPaneNew",
    "info": null,
    "iscustomlayout": false,
    "isdatareferenced": false,
    "issegmentchild": false,
    "isvisible": true,
    "kuid": "dfe3dd19ebda48b2a7959bd453a0a053",
    "layouttype": 4,
    "masterType": 0,
    "maxwidth": {
        "type": "string",
        "value": ""
    },
    "name": "kony.ui.UserWidgetInstance",
    "parent": "flxTabPaneShadow",
    "pf": "frmBBRequestHistory",
    "retaincontentalignment": false,
    "retainflexpositionproperties": false,
    "snapgridsize": 10,
    "snaptogrid": true,
    "sourceUserWidget": "g4f0753b9c12467c9de0e2bc6a812f3a",
    "wType": "UserWidgetInstance",
    "zindex": 1
}